{
  "latitude": 40.0428151,
  "longitude": -86.1274888,
  "timezone": "America/Indiana/Indianapolis",
  "currently": {
    "time": 1509584019,
    "summary": "Overcast",
    "icon": "cloudy",
    "nearestStormDistance": 0,
    "precipIntensity": 0,
    "precipProbability": 0,
    "temperature": 45.29,
    "apparentTemperature": 43.8,
    "dewPoint": 44.24,
    "humidity": 0.96,
    "pressure": 1013.19,
    "windSpeed": 3.58,
    "windGust": 8,
    "windBearing": 170,
    "cloudCover": 1,
    "uvIndex": 0,
    "visibility": 4.42,
    "ozone": 297.81
  },
  "hourly": {
    "summary": "Rain throughout the day and breezy starting tonight, continuing until tomorrow morning.",
    "icon": "rain",
    "data": [
      {
        "time": 1509580800,
        "summary": "Rain",
        "icon": "rain",
        "precipIntensity": 0.1048,
        "precipProbability": 0.88,
        "precipType": "rain",
        "temperature": 43.68,
        "apparentTemperature": 43.68,
        "dewPoint": 42.33,
        "humidity": 0.95,
        "pressure": 1013.53,
        "windSpeed": 1.57,
        "windGust": 2.9,
        "windBearing": 147,
        "cloudCover": 1,
        "uvIndex": 0,
        "visibility": 4.59,
        "ozone": 297.57
      },
      {
        "time": 1509584400,
        "summary": "Rain",
        "icon": "rain",
        "precipIntensity": 0.0797,
        "precipProbability": 0.86,
        "precipType": "rain",
        "temperature": 45.48,
        "apparentTemperature": 43.8,
        "dewPoint": 44.47,
        "humidity": 0.96,
        "pressure": 1013.15,
        "windSpeed": 3.83,
        "windGust": 8.6,
        "windBearing": 171,
        "cloudCover": 1,
        "uvIndex": 0,
        "visibility": 4.4,
        "ozone": 297.84
      },
      {
        "time": 1509588000,
        "summary": "Light Rain",
        "icon": "rain",
        "precipIntensity": 0.0458,
        "precipProbability": 0.78,
        "precipType": "rain",
        "temperature": 48.31,
        "apparentTemperature": 44.6,
        "dewPoint": 47.4,
        "humidity": 0.97,
        "pressure": 1012.75,
        "windSpeed": 8.26,
        "windGust": 18.22,
        "windBearing": 179,
        "cloudCover": 1,
        "uvIndex": 0,
        "visibility": 5.12,
        "ozone": 298.35
      },
      {
        "time": 1509591600,
        "summary": "Light Rain",
        "icon": "rain",
        "precipIntensity": 0.0253,
        "precipProbability": 0.67,
        "precipType": "rain",
        "temperature": 51.19,
        "apparentTemperature": 51.19,
        "dewPoint": 50.14,
        "humidity": 0.96,
        "pressure": 1012.42,
        "windSpeed": 12.48,
        "windGust": 27.76,
        "windBearing": 184,
        "cloudCover": 1,
        "uvIndex": 0,
        "visibility": 6.05,
        "ozone": 298.46
      },
      {
        "time": 1509595200,
        "summary": "Overcast",
        "icon": "cloudy",
        "precipIntensity": 0.0195,
        "precipProbability": 0.6,
        "precipType": "rain",
        "temperature": 53.69,
        "apparentTemperature": 53.69,
        "dewPoint": 52.24,
        "humidity": 0.95,
        "pressure": 1012.13,
        "windSpeed": 14.99,
        "windGust": 34.15,
        "windBearing": 189,
        "cloudCover": 0.98,
        "uvIndex": 0,
        "visibility": 7.26,
        "ozone": 298.1
      },
      {
        "time": 1509598800,
        "summary": "Breezy and Overcast",
        "icon": "wind",
        "precipIntensity": 0.0177,
        "precipProbability": 0.55,
        "precipType": "rain",
        "temperature": 55.87,
        "apparentTemperature": 55.87,
        "dewPoint": 53.86,
        "humidity": 0.93,
        "pressure": 1011.94,
        "windSpeed": 16.29,
        "windGust": 37.67,
        "windBearing": 194,
        "cloudCover": 0.96,
        "uvIndex": 0,
        "visibility": 8.95,
        "ozone": 297.31
      },
      {
        "time": 1509602400,
        "summary": "Windy and Overcast",
        "icon": "wind",
        "precipIntensity": 0.0166,
        "precipProbability": 0.49,
        "precipType": "rain",
        "temperature": 57.59,
        "apparentTemperature": 57.59,
        "dewPoint": 55.04,
        "humidity": 0.91,
        "pressure": 1011.85,
        "windSpeed": 17.05,
        "windGust": 39.62,
        "windBearing": 198,
        "cloudCover": 0.95,
        "uvIndex": 0,
        "visibility": 10,
        "ozone": 296.37
      },
      {
        "time": 1509606000,
        "summary": "Windy and Overcast",
        "icon": "wind",
        "precipIntensity": 0.0136,
        "precipProbability": 0.42,
        "precipType": "rain",
        "temperature": 58.55,
        "apparentTemperature": 58.55,
        "dewPoint": 55.65,
        "humidity": 0.9,
        "pressure": 1011.92,
        "windSpeed": 17.07,
        "windGust": 39.12,
        "windBearing": 199,
        "cloudCover": 0.96,
        "uvIndex": 0,
        "visibility": 10,
        "ozone": 295.16
      },
      {
        "time": 1509609600,
        "summary": "Breezy and Overcast",
        "icon": "wind",
        "precipIntensity": 0.0107,
        "precipProbability": 0.34,
        "precipType": "rain",
        "temperature": 58.91,
        "apparentTemperature": 58.91,
        "dewPoint": 55.87,
        "humidity": 0.9,
        "pressure": 1012.11,
        "windSpeed": 16.58,
        "windGust": 37.16,
        "windBearing": 197,
        "cloudCover": 0.98,
        "uvIndex": 0,
        "visibility": 10,
        "ozone": 293.74
      },
      {
        "time": 1509613200,
        "summary": "Breezy and Overcast",
        "icon": "wind",
        "precipIntensity": 0.0087,
        "precipProbability": 0.28,
        "precipType": "rain",
        "temperature": 59.09,
        "apparentTemperature": 59.09,
        "dewPoint": 55.99,
        "humidity": 0.89,
        "pressure": 1012.32,
        "windSpeed": 15.93,
        "windGust": 35.25,
        "windBearing": 197,
        "cloudCover": 1,
        "uvIndex": 0,
        "visibility": 10,
        "ozone": 292.58
      },
      {
        "time": 1509616800,
        "summary": "Breezy and Overcast",
        "icon": "wind",
        "precipIntensity": 0.0079,
        "precipProbability": 0.25,
        "precipType": "rain",
        "temperature": 59.21,
        "apparentTemperature": 59.21,
        "dewPoint": 56,
        "humidity": 0.89,
        "pressure": 1012.52,
        "windSpeed": 15.09,
        "windGust": 33.76,
        "windBearing": 196,
        "cloudCover": 1,
        "uvIndex": 0,
        "visibility": 10,
        "ozone": 291.91
      },
      {
        "time": 1509620400,
        "summary": "Overcast",
        "icon": "cloudy",
        "precipIntensity": 0.0079,
        "precipProbability": 0.23,
        "precipType": "rain",
        "temperature": 59.2,
        "apparentTemperature": 59.2,
        "dewPoint": 55.91,
        "humidity": 0.89,
        "pressure": 1012.76,
        "windSpeed": 14.09,
        "windGust": 32.28,
        "windBearing": 196,
        "cloudCover": 1,
        "uvIndex": 0,
        "visibility": 10,
        "ozone": 291.55
      },
      {
        "time": 1509624000,
        "summary": "Overcast",
        "icon": "cloudy",
        "precipIntensity": 0.0077,
        "precipProbability": 0.21,
        "precipType": "rain",
        "temperature": 59.22,
        "apparentTemperature": 59.22,
        "dewPoint": 55.96,
        "humidity": 0.89,
        "pressure": 1012.98,
        "windSpeed": 13.44,
        "windGust": 31.13,
        "windBearing": 195,
        "cloudCover": 1,
        "uvIndex": 0,
        "visibility": 10,
        "ozone": 290.93
      },
      {
        "time": 1509627600,
        "summary": "Overcast",
        "icon": "cloudy",
        "precipIntensity": 0.0065,
        "precipProbability": 0.18,
        "precipType": "rain",
        "temperature": 59.3,
        "apparentTemperature": 59.3,
        "dewPoint": 56.28,
        "humidity": 0.9,
        "pressure": 1013.26,
        "windSpeed": 13.43,
        "windGust": 30.38,
        "windBearing": 192,
        "cloudCover": 0.97,
        "uvIndex": 0,
        "visibility": 10,
        "ozone": 290.03
      },
      {
        "time": 1509631200,
        "summary": "Mostly Cloudy",
        "icon": "partly-cloudy-day",
        "precipIntensity": 0.0055,
        "precipProbability": 0.16,
        "precipType": "rain",
        "temperature": 59.33,
        "apparentTemperature": 59.33,
        "dewPoint": 56.76,
        "humidity": 0.91,
        "pressure": 1013.53,
        "windSpeed": 13.75,
        "windGust": 29.99,
        "windBearing": 188,
        "cloudCover": 0.92,
        "uvIndex": 1,
        "visibility": 10,
        "ozone": 288.95
      },
      {
        "time": 1509634800,
        "summary": "Mostly Cloudy",
        "icon": "partly-cloudy-day",
        "precipIntensity": 0.0047,
        "precipProbability": 0.14,
        "precipType": "rain",
        "temperature": 59.41,
        "apparentTemperature": 59.41,
        "dewPoint": 57.34,
        "humidity": 0.93,
        "pressure": 1013.61,
        "windSpeed": 14.17,
        "windGust": 29.75,
        "windBearing": 185,
        "cloudCover": 0.9,
        "uvIndex": 1,
        "visibility": 10,
        "ozone": 287.7
      },
      {
        "time": 1509638400,
        "summary": "Mostly Cloudy",
        "icon": "partly-cloudy-day",
        "precipIntensity": 0.0039,
        "precipProbability": 0.12,
        "precipType": "rain",
        "temperature": 59.74,
        "apparentTemperature": 59.83,
        "dewPoint": 58.04,
        "humidity": 0.94,
        "pressure": 1013.37,
        "windSpeed": 14.69,
        "windGust": 29.84,
        "windBearing": 185,
        "cloudCover": 0.93,
        "uvIndex": 1,
        "visibility": 10,
        "ozone": 286.45
      },
      {
        "time": 1509642000,
        "summary": "Overcast",
        "icon": "cloudy",
        "precipIntensity": 0.0039,
        "precipProbability": 0.12,
        "precipType": "rain",
        "temperature": 60.43,
        "apparentTemperature": 60.61,
        "dewPoint": 58.83,
        "humidity": 0.94,
        "pressure": 1012.95,
        "windSpeed": 15.3,
        "windGust": 30.15,
        "windBearing": 186,
        "cloudCover": 0.98,
        "uvIndex": 2,
        "visibility": 10,
        "ozone": 285.09
      },
      {
        "time": 1509645600,
        "summary": "Overcast",
        "icon": "cloudy",
        "precipIntensity": 0.0048,
        "precipProbability": 0.12,
        "precipType": "rain",
        "temperature": 61.3,
        "apparentTemperature": 61.54,
        "dewPoint": 59.5,
        "humidity": 0.94,
        "pressure": 1012.51,
        "windSpeed": 15.74,
        "windGust": 30.35,
        "windBearing": 186,
        "cloudCover": 1,
        "uvIndex": 2,
        "visibility": 10,
        "ozone": 283.92
      },
      {
        "time": 1509649200,
        "summary": "Overcast",
        "icon": "cloudy",
        "precipIntensity": 0.0047,
        "precipProbability": 0.12,
        "precipType": "rain",
        "temperature": 62.22,
        "apparentTemperature": 62.48,
        "dewPoint": 59.96,
        "humidity": 0.92,
        "pressure": 1012.02,
        "windSpeed": 15.81,
        "windGust": 30.27,
        "windBearing": 186,
        "cloudCover": 0.95,
        "uvIndex": 1,
        "visibility": 10,
        "ozone": 282.93
      },
      {
        "time": 1509652800,
        "summary": "Mostly Cloudy",
        "icon": "partly-cloudy-day",
        "precipIntensity": 0.0045,
        "precipProbability": 0.12,
        "precipType": "rain",
        "temperature": 63.01,
        "apparentTemperature": 63.28,
        "dewPoint": 60.31,
        "humidity": 0.91,
        "pressure": 1011.52,
        "windSpeed": 15.68,
        "windGust": 30.07,
        "windBearing": 185,
        "cloudCover": 0.87,
        "uvIndex": 1,
        "visibility": 10,
        "ozone": 281.94
      },
      {
        "time": 1509656400,
        "summary": "Mostly Cloudy",
        "icon": "partly-cloudy-day",
        "precipIntensity": 0.0054,
        "precipProbability": 0.13,
        "precipType": "rain",
        "temperature": 63.52,
        "apparentTemperature": 63.81,
        "dewPoint": 60.55,
        "humidity": 0.9,
        "pressure": 1011.26,
        "windSpeed": 15.41,
        "windGust": 29.95,
        "windBearing": 185,
        "cloudCover": 0.83,
        "uvIndex": 1,
        "visibility": 10,
        "ozone": 280.93
      },
      {
        "time": 1509660000,
        "summary": "Mostly Cloudy",
        "icon": "partly-cloudy-day",
        "precipIntensity": 0.0082,
        "precipProbability": 0.17,
        "precipType": "rain",
        "temperature": 63.58,
        "apparentTemperature": 63.88,
        "dewPoint": 60.66,
        "humidity": 0.9,
        "pressure": 1011.37,
        "windSpeed": 15.06,
        "windGust": 30.02,
        "windBearing": 185,
        "cloudCover": 0.87,
        "uvIndex": 0,
        "visibility": 10,
        "ozone": 279.77
      },
      {
        "time": 1509663600,
        "summary": "Overcast",
        "icon": "cloudy",
        "precipIntensity": 0.0132,
        "precipProbability": 0.23,
        "precipType": "rain",
        "temperature": 63.4,
        "apparentTemperature": 63.72,
        "dewPoint": 60.71,
        "humidity": 0.91,
        "pressure": 1011.71,
        "windSpeed": 14.64,
        "windGust": 30.12,
        "windBearing": 184,
        "cloudCover": 0.94,
        "uvIndex": 0,
        "visibility": 10,
        "ozone": 278.45
      },
      {
        "time": 1509667200,
        "summary": "Overcast",
        "icon": "cloudy",
        "precipIntensity": 0.0197,
        "precipProbability": 0.29,
        "precipType": "rain",
        "temperature": 63.62,
        "apparentTemperature": 63.94,
        "dewPoint": 60.85,
        "humidity": 0.91,
        "pressure": 1011.99,
        "windSpeed": 14.3,
        "windGust": 29.99,
        "windBearing": 185,
        "cloudCover": 1,
        "uvIndex": 0,
        "visibility": 10,
        "ozone": 276.9
      },
      {
        "time": 1509670800,
        "summary": "Light Rain",
        "icon": "rain",
        "precipIntensity": 0.0292,
        "precipProbability": 0.34,
        "precipType": "rain",
        "temperature": 64.24,
        "apparentTemperature": 64.6,
        "dewPoint": 61.27,
        "humidity": 0.9,
        "pressure": 1012.08,
        "windSpeed": 14.29,
        "windGust": 29.89,
        "windBearing": 193,
        "cloudCover": 1,
        "uvIndex": 0,
        "visibility": 10,
        "ozone": 274.93
      },
      {
        "time": 1509674400,
        "summary": "Light Rain",
        "icon": "rain",
        "precipIntensity": 0.0414,
        "precipProbability": 0.37,
        "precipType": "rain",
        "temperature": 65.03,
        "apparentTemperature": 65.43,
        "dewPoint": 61.78,
        "humidity": 0.89,
        "pressure": 1012.11,
        "windSpeed": 14.34,
        "windGust": 29.53,
        "windBearing": 202,
        "cloudCover": 1,
        "uvIndex": 0,
        "visibility": 10,
        "ozone": 272.74
      },
      {
        "time": 1509678000,
        "summary": "Light Rain",
        "icon": "rain",
        "precipIntensity": 0.0455,
        "precipProbability": 0.36,
        "precipType": "rain",
        "temperature": 65.38,
        "apparentTemperature": 65.8,
        "dewPoint": 62.06,
        "humidity": 0.89,
        "pressure": 1012.18,
        "windSpeed": 14.02,
        "windGust": 27.94,
        "windBearing": 205,
        "cloudCover": 1,
        "uvIndex": 0,
        "visibility": 10,
        "ozone": 270.77
      },
      {
        "time": 1509681600,
        "summary": "Light Rain",
        "icon": "rain",
        "precipIntensity": 0.0322,
        "precipProbability": 0.31,
        "precipType": "rain",
        "temperature": 65.42,
        "apparentTemperature": 65.86,
        "dewPoint": 62.18,
        "humidity": 0.89,
        "pressure": 1012.27,
        "windSpeed": 12.7,
        "windGust": 23.59,
        "windBearing": 202,
        "cloudCover": 0.99,
        "uvIndex": 0,
        "visibility": 10,
        "ozone": 269.19
      },
      {
        "time": 1509685200,
        "summary": "Overcast",
        "icon": "cloudy",
        "precipIntensity": 0.0179,
        "precipProbability": 0.24,
        "precipType": "rain",
        "temperature": 65.16,
        "apparentTemperature": 65.59,
        "dewPoint": 62.07,
        "humidity": 0.9,
        "pressure": 1012.39,
        "windSpeed": 10.85,
        "windGust": 18.02,
        "windBearing": 266,
        "cloudCover": 0.98,
        "uvIndex": 0,
        "visibility": 10,
        "ozone": 267.86
      },
      {
        "time": 1509688800,
        "summary": "Overcast",
        "icon": "cloudy",
        "precipIntensity": 0.0124,
        "precipProbability": 0.21,
        "precipType": "rain",
        "temperature": 64.46,
        "apparentTemperature": 64.82,
        "dewPoint": 61.35,
        "humidity": 0.9,
        "pressure": 1012.74,
        "windSpeed": 9.94,
        "windGust": 14.66,
        "windBearing": 248,
        "cloudCover": 0.97,
        "uvIndex": 0,
        "visibility": 10,
        "ozone": 266.89
      },
      {
        "time": 1509692400,
        "summary": "Overcast",
        "icon": "cloudy",
        "precipIntensity": 0.0089,
        "precipProbability": 0.2,
        "precipType": "rain",
        "temperature": 62.99,
        "apparentTemperature": 63.17,
        "dewPoint": 59.68,
        "humidity": 0.89,
        "pressure": 1013.4,
        "windSpeed": 10.18,
        "windGust": 15.64,
        "windBearing": 179,
        "cloudCover": 0.97,
        "uvIndex": 0,
        "visibility": 10,
        "ozone": 266.56
      },
      {
        "time": 1509696000,
        "summary": "Overcast",
        "icon": "cloudy",
        "precipIntensity": 0.0074,
        "precipProbability": 0.21,
        "precipType": "rain",
        "temperature": 61.16,
        "apparentTemperature": 61.16,
        "dewPoint": 57.41,
        "humidity": 0.87,
        "pressure": 1014.3,
        "windSpeed": 11.46,
        "windGust": 18.84,
        "windBearing": 26,
        "cloudCover": 0.98,
        "uvIndex": 0,
        "visibility": 10,
        "ozone": 266.57
      },
      {
        "time": 1509699600,
        "summary": "Overcast",
        "icon": "cloudy",
        "precipIntensity": 0.0075,
        "precipProbability": 0.23,
        "precipType": "rain",
        "temperature": 59.15,
        "apparentTemperature": 59.15,
        "dewPoint": 55.09,
        "humidity": 0.86,
        "pressure": 1015.38,
        "windSpeed": 12.29,
        "windGust": 21.34,
        "windBearing": 339,
        "cloudCover": 0.97,
        "uvIndex": 0,
        "visibility": 10,
        "ozone": 266.38
      },
      {
        "time": 1509703200,
        "summary": "Overcast",
        "icon": "cloudy",
        "precipIntensity": 0.0052,
        "precipProbability": 0.2,
        "precipType": "rain",
        "temperature": 56.99,
        "apparentTemperature": 56.99,
        "dewPoint": 52.75,
        "humidity": 0.86,
        "pressure": 1016.7,
        "windSpeed": 12.37,
        "windGust": 22.08,
        "windBearing": 331,
        "cloudCover": 0.94,
        "uvIndex": 0,
        "visibility": 10,
        "ozone": 265.59
      },
      {
        "time": 1509706800,
        "summary": "Mostly Cloudy",
        "icon": "partly-cloudy-night",
        "precipIntensity": 0.0028,
        "precipProbability": 0.16,
        "precipType": "rain",
        "temperature": 54.74,
        "apparentTemperature": 54.74,
        "dewPoint": 50.35,
        "humidity": 0.85,
        "pressure": 1018.21,
        "windSpeed": 12.16,
        "windGust": 22.1,
        "windBearing": 345,
        "cloudCover": 0.9,
        "uvIndex": 0,
        "visibility": 10,
        "ozone": 264.5
      },
      {
        "time": 1509710400,
        "summary": "Mostly Cloudy",
        "icon": "partly-cloudy-night",
        "precipIntensity": 0.0017,
        "precipProbability": 0.12,
        "precipType": "rain",
        "temperature": 52.57,
        "apparentTemperature": 52.57,
        "dewPoint": 48.41,
        "humidity": 0.86,
        "pressure": 1019.58,
        "windSpeed": 12.08,
        "windGust": 21.72,
        "windBearing": 359,
        "cloudCover": 0.85,
        "uvIndex": 0,
        "visibility": 10,
        "ozone": 263.48
      },
      {
        "time": 1509714000,
        "summary": "Mostly Cloudy",
        "icon": "partly-cloudy-day",
        "precipIntensity": 0.0008,
        "precipProbability": 0.07,
        "precipType": "rain",
        "temperature": 51.18,
        "apparentTemperature": 51.18,
        "dewPoint": 47.14,
        "humidity": 0.86,
        "pressure": 1020.73,
        "windSpeed": 12.46,
        "windGust": 20.87,
        "windBearing": 6,
        "cloudCover": 0.76,
        "uvIndex": 0,
        "visibility": 10,
        "ozone": 262.91
      },
      {
        "time": 1509717600,
        "summary": "Mostly Cloudy",
        "icon": "partly-cloudy-day",
        "precipIntensity": 0.0002,
        "precipProbability": 0.02,
        "precipType": "rain",
        "temperature": 50.35,
        "apparentTemperature": 50.35,
        "dewPoint": 46.29,
        "humidity": 0.86,
        "pressure": 1021.77,
        "windSpeed": 13.01,
        "windGust": 19.6,
        "windBearing": 10,
        "cloudCover": 0.64,
        "uvIndex": 1,
        "visibility": 10,
        "ozone": 262.46
      },
      {
        "time": 1509721200,
        "summary": "Partly Cloudy",
        "icon": "partly-cloudy-day",
        "precipIntensity": 0,
        "precipProbability": 0,
        "temperature": 50.31,
        "apparentTemperature": 50.31,
        "dewPoint": 45.67,
        "humidity": 0.84,
        "pressure": 1022.56,
        "windSpeed": 13.23,
        "windGust": 18.4,
        "windBearing": 13,
        "cloudCover": 0.54,
        "uvIndex": 1,
        "visibility": 10,
        "ozone": 262.01
      },
      {
        "time": 1509724800,
        "summary": "Partly Cloudy",
        "icon": "partly-cloudy-day",
        "precipIntensity": 0,
        "precipProbability": 0,
        "temperature": 51.27,
        "apparentTemperature": 51.27,
        "dewPoint": 45.32,
        "humidity": 0.8,
        "pressure": 1023,
        "windSpeed": 12.8,
        "windGust": 17.24,
        "windBearing": 16,
        "cloudCover": 0.49,
        "uvIndex": 2,
        "visibility": 10,
        "ozone": 261.58
      },
      {
        "time": 1509728400,
        "summary": "Partly Cloudy",
        "icon": "partly-cloudy-day",
        "precipIntensity": 0,
        "precipProbability": 0,
        "temperature": 52.96,
        "apparentTemperature": 52.96,
        "dewPoint": 45.16,
        "humidity": 0.75,
        "pressure": 1023.2,
        "windSpeed": 12,
        "windGust": 16.08,
        "windBearing": 18,
        "cloudCover": 0.45,
        "uvIndex": 2,
        "visibility": 10,
        "ozone": 261.13
      },
      {
        "time": 1509732000,
        "summary": "Partly Cloudy",
        "icon": "partly-cloudy-day",
        "precipIntensity": 0,
        "precipProbability": 0,
        "temperature": 54.54,
        "apparentTemperature": 54.54,
        "dewPoint": 45.02,
        "humidity": 0.7,
        "pressure": 1023.27,
        "windSpeed": 11.35,
        "windGust": 15.17,
        "windBearing": 20,
        "cloudCover": 0.38,
        "uvIndex": 2,
        "visibility": 10,
        "ozone": 260.51
      },
      {
        "time": 1509735600,
        "summary": "Partly Cloudy",
        "icon": "partly-cloudy-day",
        "precipIntensity": 0,
        "precipProbability": 0,
        "temperature": 55.67,
        "apparentTemperature": 55.67,
        "dewPoint": 44.86,
        "humidity": 0.67,
        "pressure": 1023.11,
        "windSpeed": 11.09,
        "windGust": 14.49,
        "windBearing": 24,
        "cloudCover": 0.26,
        "uvIndex": 2,
        "visibility": 10,
        "ozone": 259.67
      },
      {
        "time": 1509739200,
        "summary": "Clear",
        "icon": "clear-day",
        "precipIntensity": 0,
        "precipProbability": 0,
        "temperature": 56.11,
        "apparentTemperature": 56.11,
        "dewPoint": 44.65,
        "humidity": 0.65,
        "pressure": 1022.84,
        "windSpeed": 10.97,
        "windGust": 14.03,
        "windBearing": 28,
        "cloudCover": 0.12,
        "uvIndex": 2,
        "visibility": 10,
        "ozone": 258.72
      },
      {
        "time": 1509742800,
        "summary": "Clear",
        "icon": "clear-day",
        "precipIntensity": 0,
        "precipProbability": 0,
        "temperature": 55.54,
        "apparentTemperature": 55.54,
        "dewPoint": 44.34,
        "humidity": 0.66,
        "pressure": 1022.78,
        "windSpeed": 10.63,
        "windGust": 14.09,
        "windBearing": 32,
        "cloudCover": 0.02,
        "uvIndex": 1,
        "visibility": 10,
        "ozone": 257.84
      },
      {
        "time": 1509746400,
        "summary": "Clear",
        "icon": "clear-day",
        "precipIntensity": 0.0001,
        "precipProbability": 0.02,
        "precipType": "rain",
        "temperature": 53.9,
        "apparentTemperature": 53.9,
        "dewPoint": 43.81,
        "humidity": 0.69,
        "pressure": 1023.22,
        "windSpeed": 9.8,
        "windGust": 15,
        "windBearing": 35,
        "cloudCover": 0,
        "uvIndex": 0,
        "visibility": 10,
        "ozone": 257.1
      },
      {
        "time": 1509750000,
        "summary": "Clear",
        "icon": "clear-night",
        "precipIntensity": 0.0001,
        "precipProbability": 0.02,
        "precipType": "rain",
        "temperature": 51.6,
        "apparentTemperature": 51.6,
        "dewPoint": 43.16,
        "humidity": 0.73,
        "pressure": 1023.9,
        "windSpeed": 8.76,
        "windGust": 16.45,
        "windBearing": 38,
        "cloudCover": 0,
        "uvIndex": 0,
        "visibility": 10,
        "ozone": 256.34
      },
      {
        "time": 1509753600,
        "summary": "Clear",
        "icon": "clear-night",
        "precipIntensity": 0.0001,
        "precipProbability": 0.02,
        "precipType": "rain",
        "temperature": 49.74,
        "apparentTemperature": 46.41,
        "dewPoint": 42.54,
        "humidity": 0.76,
        "pressure": 1024.48,
        "windSpeed": 8.11,
        "windGust": 17.76,
        "windBearing": 42,
        "cloudCover": 0,
        "uvIndex": 0,
        "visibility": 10,
        "ozone": 255.86
      },
      {
        "time": 1509757200,
        "summary": "Clear",
        "icon": "clear-night",
        "precipIntensity": 0,
        "precipProbability": 0,
        "temperature": 48.14,
        "apparentTemperature": 44.45,
        "dewPoint": 42.06,
        "humidity": 0.79,
        "pressure": 1024.81,
        "windSpeed": 8.13,
        "windGust": 18.72,
        "windBearing": 49,
        "cloudCover": 0.03,
        "uvIndex": 0,
        "visibility": 10,
        "ozone": 255.7
      },
      {
        "time": 1509760800,
        "summary": "Clear",
        "icon": "clear-night",
        "precipIntensity": 0,
        "precipProbability": 0,
        "temperature": 46.74,
        "apparentTemperature": 42.57,
        "dewPoint": 41.64,
        "humidity": 0.82,
        "pressure": 1025.06,
        "windSpeed": 8.52,
        "windGust": 19.52,
        "windBearing": 57,
        "cloudCover": 0.06,
        "uvIndex": 0,
        "visibility": 10,
        "ozone": 255.76
      },
      {
        "time": 1509764400,
        "summary": "Clear",
        "icon": "clear-night",
        "precipIntensity": 0,
        "precipProbability": 0,
        "temperature": 45.57,
        "apparentTemperature": 40.98,
        "dewPoint": 41.15,
        "humidity": 0.84,
        "pressure": 1025.15,
        "windSpeed": 8.9,
        "windGust": 20.08,
        "windBearing": 65,
        "cloudCover": 0.09,
        "uvIndex": 0,
        "visibility": 10,
        "ozone": 255.93
      },
      {
        "time": 1509768000,
        "summary": "Clear",
        "icon": "clear-night",
        "precipIntensity": 0.0001,
        "precipProbability": 0.02,
        "precipType": "rain",
        "temperature": 44.88,
        "apparentTemperature": 40.03,
        "dewPoint": 40.5,
        "humidity": 0.85,
        "pressure": 1025.03,
        "windSpeed": 9.14,
        "windGust": 20.3,
        "windBearing": 73,
        "cloudCover": 0.15,
        "uvIndex": 0,
        "visibility": 10,
        "ozone": 256.16
      },
      {
        "time": 1509771600,
        "summary": "Clear",
        "icon": "clear-night",
        "precipIntensity": 0.0002,
        "precipProbability": 0.02,
        "precipType": "rain",
        "temperature": 44.6,
        "apparentTemperature": 39.59,
        "dewPoint": 39.77,
        "humidity": 0.83,
        "pressure": 1024.72,
        "windSpeed": 9.37,
        "windGust": 20.32,
        "windBearing": 82,
        "cloudCover": 0.23,
        "uvIndex": 0,
        "visibility": 10,
        "ozone": 256.44
      },
      {
        "time": 1509775200,
        "summary": "Partly Cloudy",
        "icon": "partly-cloudy-night",
        "precipIntensity": 0.0002,
        "precipProbability": 0.02,
        "precipType": "rain",
        "temperature": 44.46,
        "apparentTemperature": 39.37,
        "dewPoint": 39.19,
        "humidity": 0.82,
        "pressure": 1024.43,
        "windSpeed": 9.5,
        "windGust": 20.37,
        "windBearing": 89,
        "cloudCover": 0.3,
        "uvIndex": 0,
        "visibility": 10,
        "ozone": 256.76
      },
      {
        "time": 1509778800,
        "summary": "Partly Cloudy",
        "icon": "partly-cloudy-night",
        "precipIntensity": 0.0002,
        "precipProbability": 0.02,
        "precipType": "rain",
        "temperature": 44.06,
        "apparentTemperature": 38.88,
        "dewPoint": 38.85,
        "humidity": 0.82,
        "pressure": 1024.13,
        "windSpeed": 9.48,
        "windGust": 20.57,
        "windBearing": 95,
        "cloudCover": 0.36,
        "uvIndex": 0,
        "visibility": 10,
        "ozone": 256.75
      },
      {
        "time": 1509782400,
        "summary": "Partly Cloudy",
        "icon": "partly-cloudy-night",
        "precipIntensity": 0.0001,
        "precipProbability": 0.02,
        "precipType": "rain",
        "temperature": 43.54,
        "apparentTemperature": 38.27,
        "dewPoint": 38.62,
        "humidity": 0.83,
        "pressure": 1023.81,
        "windSpeed": 9.4,
        "windGust": 20.79,
        "windBearing": 99,
        "cloudCover": 0.41,
        "uvIndex": 0,
        "visibility": 10,
        "ozone": 256.64
      },
      {
        "time": 1509786000,
        "summary": "Partly Cloudy",
        "icon": "partly-cloudy-night",
        "precipIntensity": 0.0001,
        "precipProbability": 0.02,
        "precipType": "rain",
        "temperature": 42.82,
        "apparentTemperature": 37.45,
        "dewPoint": 38.47,
        "humidity": 0.84,
        "pressure": 1023.53,
        "windSpeed": 9.27,
        "windGust": 20.87,
        "windBearing": 104,
        "cloudCover": 0.46,
        "uvIndex": 0,
        "visibility": 10,
        "ozone": 256.79
      },
      {
        "time": 1509789600,
        "summary": "Partly Cloudy",
        "icon": "partly-cloudy-night",
        "precipIntensity": 0,
        "precipProbability": 0,
        "temperature": 42.32,
        "apparentTemperature": 36.93,
        "dewPoint": 38.33,
        "humidity": 0.86,
        "pressure": 1023.33,
        "windSpeed": 9.04,
        "windGust": 20.72,
        "windBearing": 106,
        "cloudCover": 0.51,
        "uvIndex": 0,
        "visibility": 10,
        "ozone": 257.68
      },
      {
        "time": 1509793200,
        "summary": "Partly Cloudy",
        "icon": "partly-cloudy-night",
        "precipIntensity": 0,
        "precipProbability": 0,
        "temperature": 42.14,
        "apparentTemperature": 36.82,
        "dewPoint": 38.25,
        "humidity": 0.86,
        "pressure": 1023.18,
        "windSpeed": 8.8,
        "windGust": 20.42,
        "windBearing": 109,
        "cloudCover": 0.56,
        "uvIndex": 0,
        "visibility": 10,
        "ozone": 258.84
      },
      {
        "time": 1509796800,
        "summary": "Mostly Cloudy",
        "icon": "partly-cloudy-night",
        "precipIntensity": 0,
        "precipProbability": 0,
        "temperature": 42.73,
        "apparentTemperature": 37.52,
        "dewPoint": 38.5,
        "humidity": 0.85,
        "pressure": 1022.97,
        "windSpeed": 8.84,
        "windGust": 20.03,
        "windBearing": 112,
        "cloudCover": 0.6,
        "uvIndex": 0,
        "visibility": 10,
        "ozone": 260.21
      },
      {
        "time": 1509800400,
        "summary": "Mostly Cloudy",
        "icon": "partly-cloudy-day",
        "precipIntensity": 0.0003,
        "precipProbability": 0.03,
        "precipType": "rain",
        "temperature": 44.08,
        "apparentTemperature": 38.93,
        "dewPoint": 39.19,
        "humidity": 0.83,
        "pressure": 1022.75,
        "windSpeed": 9.44,
        "windGust": 19.56,
        "windBearing": 116,
        "cloudCover": 0.66,
        "uvIndex": 0,
        "visibility": 10,
        "ozone": 261.66
      },
      {
        "time": 1509804000,
        "summary": "Mostly Cloudy",
        "icon": "partly-cloudy-day",
        "precipIntensity": 0.0011,
        "precipProbability": 0.08,
        "precipType": "rain",
        "temperature": 45.83,
        "apparentTemperature": 40.75,
        "dewPoint": 40.28,
        "humidity": 0.81,
        "pressure": 1022.47,
        "windSpeed": 10.33,
        "windGust": 19,
        "windBearing": 120,
        "cloudCover": 0.73,
        "uvIndex": 1,
        "visibility": 10,
        "ozone": 263.35
      },
      {
        "time": 1509807600,
        "summary": "Mostly Cloudy",
        "icon": "partly-cloudy-day",
        "precipIntensity": 0.0019,
        "precipProbability": 0.12,
        "precipType": "rain",
        "temperature": 47.38,
        "apparentTemperature": 42.47,
        "dewPoint": 41.59,
        "humidity": 0.8,
        "pressure": 1021.94,
        "windSpeed": 10.92,
        "windGust": 18.5,
        "windBearing": 125,
        "cloudCover": 0.79,
        "uvIndex": 1,
        "visibility": 10,
        "ozone": 265.08
      },
      {
        "time": 1509811200,
        "summary": "Mostly Cloudy",
        "icon": "partly-cloudy-day",
        "precipIntensity": 0.0019,
        "precipProbability": 0.12,
        "precipType": "rain",
        "temperature": 49.05,
        "apparentTemperature": 44.54,
        "dewPoint": 43.27,
        "humidity": 0.8,
        "pressure": 1021.01,
        "windSpeed": 10.98,
        "windGust": 18.03,
        "windBearing": 131,
        "cloudCover": 0.82,
        "uvIndex": 1,
        "visibility": 10,
        "ozone": 266.87
      },
      {
        "time": 1509814800,
        "summary": "Mostly Cloudy",
        "icon": "partly-cloudy-day",
        "precipIntensity": 0.0017,
        "precipProbability": 0.12,
        "precipType": "rain",
        "temperature": 50.86,
        "apparentTemperature": 50.86,
        "dewPoint": 45.16,
        "humidity": 0.81,
        "pressure": 1019.85,
        "windSpeed": 10.75,
        "windGust": 17.62,
        "windBearing": 137,
        "cloudCover": 0.84,
        "uvIndex": 2,
        "visibility": 10,
        "ozone": 268.8
      },
      {
        "time": 1509818400,
        "summary": "Mostly Cloudy",
        "icon": "partly-cloudy-day",
        "precipIntensity": 0.0016,
        "precipProbability": 0.12,
        "precipType": "rain",
        "temperature": 52.55,
        "apparentTemperature": 52.55,
        "dewPoint": 46.97,
        "humidity": 0.81,
        "pressure": 1018.75,
        "windSpeed": 10.53,
        "windGust": 17.37,
        "windBearing": 142,
        "cloudCover": 0.84,
        "uvIndex": 2,
        "visibility": 10,
        "ozone": 270.75
      },
      {
        "time": 1509822000,
        "summary": "Mostly Cloudy",
        "icon": "partly-cloudy-day",
        "precipIntensity": 0.0014,
        "precipProbability": 0.11,
        "precipType": "rain",
        "temperature": 54.08,
        "apparentTemperature": 54.08,
        "dewPoint": 48.62,
        "humidity": 0.82,
        "pressure": 1017.79,
        "windSpeed": 10.4,
        "windGust": 17.36,
        "windBearing": 147,
        "cloudCover": 0.8,
        "uvIndex": 1,
        "visibility": 10,
        "ozone": 273.04
      },
      {
        "time": 1509825600,
        "summary": "Mostly Cloudy",
        "icon": "partly-cloudy-day",
        "precipIntensity": 0.0012,
        "precipProbability": 0.09,
        "precipType": "rain",
        "temperature": 55.4,
        "apparentTemperature": 55.4,
        "dewPoint": 50.14,
        "humidity": 0.82,
        "pressure": 1016.92,
        "windSpeed": 10.3,
        "windGust": 17.52,
        "windBearing": 151,
        "cloudCover": 0.74,
        "uvIndex": 1,
        "visibility": 10,
        "ozone": 275.41
      },
      {
        "time": 1509829200,
        "summary": "Mostly Cloudy",
        "icon": "partly-cloudy-day",
        "precipIntensity": 0.0011,
        "precipProbability": 0.08,
        "precipType": "rain",
        "temperature": 56.22,
        "apparentTemperature": 56.22,
        "dewPoint": 51.27,
        "humidity": 0.83,
        "pressure": 1016.22,
        "windSpeed": 10.17,
        "windGust": 17.65,
        "windBearing": 153,
        "cloudCover": 0.7,
        "uvIndex": 1,
        "visibility": 10,
        "ozone": 277.47
      },
      {
        "time": 1509832800,
        "summary": "Mostly Cloudy",
        "icon": "partly-cloudy-day",
        "precipIntensity": 0.0006,
        "precipProbability": 0.07,
        "precipType": "rain",
        "temperature": 56.21,
        "apparentTemperature": 56.21,
        "dewPoint": 51.74,
        "humidity": 0.85,
        "pressure": 1015.82,
        "windSpeed": 9.96,
        "windGust": 17.51,
        "windBearing": 154,
        "cloudCover": 0.67,
        "uvIndex": 0,
        "visibility": 10,
        "ozone": 279.22
      },
      {
        "time": 1509836400,
        "summary": "Mostly Cloudy",
        "icon": "partly-cloudy-night",
        "precipIntensity": 0.0002,
        "precipProbability": 0.04,
        "precipType": "rain",
        "temperature": 55.73,
        "apparentTemperature": 55.73,
        "dewPoint": 51.84,
        "humidity": 0.87,
        "pressure": 1015.63,
        "windSpeed": 9.72,
        "windGust": 17.34,
        "windBearing": 152,
        "cloudCover": 0.66,
        "uvIndex": 0,
        "visibility": 10,
        "ozone": 280.77
      },
      {
        "time": 1509840000,
        "summary": "Mostly Cloudy",
        "icon": "partly-cloudy-night",
        "precipIntensity": 0.0001,
        "precipProbability": 0.03,
        "precipType": "rain",
        "temperature": 55.51,
        "apparentTemperature": 55.51,
        "dewPoint": 52.07,
        "humidity": 0.88,
        "pressure": 1015.44,
        "windSpeed": 9.68,
        "windGust": 17.69,
        "windBearing": 153,
        "cloudCover": 0.65,
        "uvIndex": 0,
        "visibility": 10,
        "ozone": 281.09
      },
      {
        "time": 1509843600,
        "summary": "Mostly Cloudy",
        "icon": "partly-cloudy-night",
        "precipIntensity": 0.0003,
        "precipProbability": 0.06,
        "precipType": "rain",
        "temperature": 55.87,
        "apparentTemperature": 55.87,
        "dewPoint": 52.7,
        "humidity": 0.89,
        "pressure": 1015.2,
        "windSpeed": 10.02,
        "windGust": 19.22,
        "windBearing": 157,
        "cloudCover": 0.71,
        "uvIndex": 0,
        "visibility": 10,
        "ozone": 279.72
      },
      {
        "time": 1509847200,
        "summary": "Mostly Cloudy",
        "icon": "partly-cloudy-night",
        "precipIntensity": 0.0011,
        "precipProbability": 0.1,
        "precipType": "rain",
        "temperature": 56.45,
        "apparentTemperature": 56.45,
        "dewPoint": 53.49,
        "humidity": 0.9,
        "pressure": 1014.95,
        "windSpeed": 10.58,
        "windGust": 21.23,
        "windBearing": 163,
        "cloudCover": 0.81,
        "uvIndex": 0,
        "visibility": 10,
        "ozone": 277.34
      },
      {
        "time": 1509850800,
        "summary": "Mostly Cloudy",
        "icon": "partly-cloudy-night",
        "precipIntensity": 0.0025,
        "precipProbability": 0.12,
        "precipType": "rain",
        "temperature": 57.02,
        "apparentTemperature": 57.02,
        "dewPoint": 54.22,
        "humidity": 0.9,
        "pressure": 1014.71,
        "windSpeed": 10.97,
        "windGust": 22.44,
        "windBearing": 169,
        "cloudCover": 0.88,
        "uvIndex": 0,
        "visibility": 10,
        "ozone": 275.4
      },
      {
        "time": 1509854400,
        "summary": "Mostly Cloudy",
        "icon": "partly-cloudy-night",
        "precipIntensity": 0.0044,
        "precipProbability": 0.13,
        "precipType": "rain",
        "temperature": 57.55,
        "apparentTemperature": 57.55,
        "dewPoint": 54.79,
        "humidity": 0.91,
        "pressure": 1014.43,
        "windSpeed": 10.93,
        "windGust": 22.09,
        "windBearing": 175,
        "cloudCover": 0.9,
        "uvIndex": 0,
        "visibility": 10,
        "ozone": 274.59
      },
      {
        "time": 1509858000,
        "summary": "Mostly Cloudy",
        "icon": "partly-cloudy-night",
        "precipIntensity": 0.0073,
        "precipProbability": 0.15,
        "precipType": "rain",
        "temperature": 58.19,
        "apparentTemperature": 58.19,
        "dewPoint": 55.31,
        "humidity": 0.9,
        "pressure": 1014.12,
        "windSpeed": 10.72,
        "windGust": 20.97,
        "windBearing": 179,
        "cloudCover": 0.88,
        "uvIndex": 0,
        "visibility": 10,
        "ozone": 274.28
      },
      {
        "time": 1509861600,
        "summary": "Mostly Cloudy",
        "icon": "partly-cloudy-night",
        "precipIntensity": 0.0101,
        "precipProbability": 0.16,
        "precipType": "rain",
        "temperature": 58.93,
        "apparentTemperature": 58.93,
        "dewPoint": 55.8,
        "humidity": 0.89,
        "pressure": 1013.86,
        "windSpeed": 10.6,
        "windGust": 20.1,
        "windBearing": 183,
        "cloudCover": 0.87,
        "uvIndex": 0,
        "visibility": 10,
        "ozone": 274.15
      },
      {
        "time": 1509865200,
        "summary": "Overcast",
        "icon": "cloudy",
        "precipIntensity": 0.0028,
        "precipProbability": 0.11,
        "precipType": "rain",
        "temperature": 60.5,
        "apparentTemperature": 60.5,
        "dewPoint": 57.28,
        "humidity": 0.89,
        "pressure": 1013.45,
        "windSpeed": 10.15,
        "windGust": 22.51,
        "windBearing": 181,
        "cloudCover": 0.95,
        "uvIndex": 0,
        "ozone": 274.2
      },
      {
        "time": 1509868800,
        "summary": "Overcast",
        "icon": "cloudy",
        "precipIntensity": 0.0045,
        "precipProbability": 0.11,
        "precipType": "rain",
        "temperature": 61.52,
        "apparentTemperature": 61.57,
        "dewPoint": 58.37,
        "humidity": 0.89,
        "pressure": 1012.99,
        "windSpeed": 10.44,
        "windGust": 22.26,
        "windBearing": 181,
        "cloudCover": 0.96,
        "uvIndex": 0,
        "ozone": 274.37
      },
      {
        "time": 1509872400,
        "summary": "Overcast",
        "icon": "cloudy",
        "precipIntensity": 0.0068,
        "precipProbability": 0.12,
        "precipType": "rain",
        "temperature": 62.29,
        "apparentTemperature": 62.46,
        "dewPoint": 59.36,
        "humidity": 0.9,
        "pressure": 1012.6,
        "windSpeed": 10.69,
        "windGust": 22.57,
        "windBearing": 183,
        "cloudCover": 0.97,
        "uvIndex": 0,
        "ozone": 274.37
      },
      {
        "time": 1509876000,
        "summary": "Overcast",
        "icon": "cloudy",
        "precipIntensity": 0.0088,
        "precipProbability": 0.13,
        "precipType": "rain",
        "temperature": 62.78,
        "apparentTemperature": 63.03,
        "dewPoint": 60.1,
        "humidity": 0.91,
        "pressure": 1012.35,
        "windSpeed": 10.85,
        "windGust": 23.9,
        "windBearing": 186,
        "cloudCover": 0.98,
        "uvIndex": 0,
        "ozone": 274.15
      },
      {
        "time": 1509879600,
        "summary": "Overcast",
        "icon": "cloudy",
        "precipIntensity": 0.0112,
        "precipProbability": 0.13,
        "precipType": "rain",
        "temperature": 63.14,
        "apparentTemperature": 63.47,
        "dewPoint": 60.73,
        "humidity": 0.92,
        "pressure": 1012.22,
        "windSpeed": 10.96,
        "windGust": 25.76,
        "windBearing": 191,
        "cloudCover": 0.99,
        "uvIndex": 0,
        "ozone": 273.7
      },
      {
        "time": 1509883200,
        "summary": "Overcast",
        "icon": "cloudy",
        "precipIntensity": 0.0124,
        "precipProbability": 0.13,
        "precipType": "rain",
        "temperature": 63.41,
        "apparentTemperature": 63.82,
        "dewPoint": 61.32,
        "humidity": 0.93,
        "pressure": 1012.12,
        "windSpeed": 11.22,
        "windGust": 27.46,
        "windBearing": 194,
        "cloudCover": 0.99,
        "uvIndex": 0,
        "ozone": 273.06
      },
      {
        "time": 1509886800,
        "summary": "Overcast",
        "icon": "cloudy",
        "precipIntensity": 0.01,
        "precipProbability": 0.11,
        "precipType": "rain",
        "temperature": 63.66,
        "apparentTemperature": 64.13,
        "dewPoint": 61.84,
        "humidity": 0.94,
        "pressure": 1012.09,
        "windSpeed": 11.68,
        "windGust": 28.64,
        "windBearing": 197,
        "cloudCover": 0.99,
        "uvIndex": 0,
        "ozone": 271.98
      },
      {
        "time": 1509890400,
        "summary": "Overcast",
        "icon": "cloudy",
        "precipIntensity": 0.0066,
        "precipProbability": 0.09,
        "precipType": "rain",
        "temperature": 63.81,
        "apparentTemperature": 64.35,
        "dewPoint": 62.32,
        "humidity": 0.95,
        "pressure": 1012.13,
        "windSpeed": 12.3,
        "windGust": 29.63,
        "windBearing": 198,
        "cloudCover": 1,
        "uvIndex": 0,
        "ozone": 270.72
      },
      {
        "time": 1509894000,
        "summary": "Overcast",
        "icon": "cloudy",
        "precipIntensity": 0.0047,
        "precipProbability": 0.08,
        "precipType": "rain",
        "temperature": 63.99,
        "apparentTemperature": 64.6,
        "dewPoint": 62.78,
        "humidity": 0.96,
        "pressure": 1012,
        "windSpeed": 13.08,
        "windGust": 30.71,
        "windBearing": 199,
        "cloudCover": 1,
        "uvIndex": 1,
        "ozone": 269.67
      },
      {
        "time": 1509897600,
        "summary": "Overcast",
        "icon": "cloudy",
        "precipIntensity": 0.0038,
        "precipProbability": 0.07,
        "precipType": "rain",
        "temperature": 64.53,
        "apparentTemperature": 65.18,
        "dewPoint": 63.26,
        "humidity": 0.96,
        "pressure": 1011.58,
        "windSpeed": 14.2,
        "windGust": 32.01,
        "windBearing": 200,
        "cloudCover": 1,
        "uvIndex": 1,
        "ozone": 268.78
      },
      {
        "time": 1509901200,
        "summary": "Overcast",
        "icon": "cloudy",
        "precipIntensity": 0.0033,
        "precipProbability": 0.07,
        "precipType": "rain",
        "temperature": 65.39,
        "apparentTemperature": 66.06,
        "dewPoint": 63.73,
        "humidity": 0.94,
        "pressure": 1010.98,
        "windSpeed": 15.43,
        "windGust": 33.4,
        "windBearing": 201,
        "cloudCover": 0.99,
        "uvIndex": 2,
        "ozone": 268.12
      },
      {
        "time": 1509904800,
        "summary": "Overcast",
        "icon": "cloudy",
        "precipIntensity": 0.0031,
        "precipProbability": 0.06,
        "precipType": "rain",
        "temperature": 66.21,
        "apparentTemperature": 66.9,
        "dewPoint": 64.12,
        "humidity": 0.93,
        "pressure": 1010.44,
        "windSpeed": 16.24,
        "windGust": 34.79,
        "windBearing": 201,
        "cloudCover": 0.99,
        "uvIndex": 2,
        "ozone": 267.81
      },
      {
        "time": 1509908400,
        "summary": "Overcast",
        "icon": "cloudy",
        "precipIntensity": 0.004,
        "precipProbability": 0.07,
        "precipType": "rain",
        "temperature": 66.71,
        "apparentTemperature": 67.41,
        "dewPoint": 64.36,
        "humidity": 0.92,
        "pressure": 1009.92,
        "windSpeed": 16.24,
        "windGust": 36.32,
        "windBearing": 202,
        "cloudCover": 0.99,
        "uvIndex": 1,
        "ozone": 267.87
      },
      {
        "time": 1509912000,
        "summary": "Overcast",
        "icon": "cloudy",
        "precipIntensity": 0.0072,
        "precipProbability": 0.08,
        "precipType": "rain",
        "temperature": 66.86,
        "apparentTemperature": 67.57,
        "dewPoint": 64.52,
        "humidity": 0.92,
        "pressure": 1009.45,
        "windSpeed": 15.83,
        "windGust": 37.85,
        "windBearing": 201,
        "cloudCover": 1,
        "uvIndex": 1,
        "ozone": 268.28
      },
      {
        "time": 1509915600,
        "summary": "Overcast",
        "icon": "cloudy",
        "precipIntensity": 0.0092,
        "precipProbability": 0.09,
        "precipType": "rain",
        "temperature": 66.99,
        "apparentTemperature": 67.73,
        "dewPoint": 64.68,
        "humidity": 0.92,
        "pressure": 1009.12,
        "windSpeed": 15.53,
        "windGust": 38.89,
        "windBearing": 202,
        "cloudCover": 1,
        "uvIndex": 0,
        "ozone": 268.9
      },
      {
        "time": 1509919200,
        "summary": "Windy and Overcast",
        "icon": "wind",
        "precipIntensity": 0.0058,
        "precipProbability": 0.1,
        "precipType": "rain",
        "temperature": 67.26,
        "apparentTemperature": 68.02,
        "dewPoint": 64.94,
        "humidity": 0.92,
        "pressure": 1009,
        "windSpeed": 15.42,
        "windGust": 39.07,
        "windBearing": 203,
        "cloudCover": 1,
        "uvIndex": 0,
        "ozone": 269.72
      },
      {
        "time": 1509922800,
        "summary": "Overcast",
        "icon": "cloudy",
        "precipIntensity": 0.002,
        "precipProbability": 0.1,
        "precipType": "rain",
        "temperature": 67.57,
        "apparentTemperature": 68.36,
        "dewPoint": 65.22,
        "humidity": 0.92,
        "pressure": 1009.03,
        "windSpeed": 15.41,
        "windGust": 38.77,
        "windBearing": 205,
        "cloudCover": 1,
        "uvIndex": 0,
        "ozone": 270.81
      },
      {
        "time": 1509926400,
        "summary": "Breezy and Overcast",
        "icon": "wind",
        "precipIntensity": 0.0016,
        "precipProbability": 0.12,
        "precipType": "rain",
        "temperature": 67.81,
        "apparentTemperature": 68.62,
        "dewPoint": 65.41,
        "humidity": 0.92,
        "pressure": 1009.09,
        "windSpeed": 15.81,
        "windGust": 38.56,
        "windBearing": 208,
        "cloudCover": 1,
        "uvIndex": 0,
        "ozone": 271.74
      },
      {
        "time": 1509930000,
        "summary": "Breezy and Overcast",
        "icon": "wind",
        "precipIntensity": 0.0026,
        "precipProbability": 0.16,
        "precipType": "rain",
        "temperature": 67.92,
        "apparentTemperature": 68.74,
        "dewPoint": 65.55,
        "humidity": 0.92,
        "pressure": 1009.11,
        "windSpeed": 17.13,
        "windGust": 38.93,
        "windBearing": 210,
        "cloudCover": 1,
        "uvIndex": 0,
        "ozone": 272.26
      },
      {
        "time": 1509933600,
        "summary": "Windy and Overcast",
        "icon": "wind",
        "precipIntensity": 0.0047,
        "precipProbability": 0.21,
        "precipType": "rain",
        "temperature": 67.83,
        "apparentTemperature": 68.67,
        "dewPoint": 65.63,
        "humidity": 0.93,
        "pressure": 1009.17,
        "windSpeed": 18.85,
        "windGust": 39.42,
        "windBearing": 212,
        "cloudCover": 1,
        "uvIndex": 0,
        "ozone": 272.73
      },
      {
        "time": 1509937200,
        "summary": "Windy and Overcast",
        "icon": "wind",
        "precipIntensity": 0.0088,
        "precipProbability": 0.26,
        "precipType": "rain",
        "temperature": 67.52,
        "apparentTemperature": 68.33,
        "dewPoint": 65.36,
        "humidity": 0.93,
        "pressure": 1009.31,
        "windSpeed": 19.64,
        "windGust": 39.3,
        "windBearing": 217,
        "cloudCover": 1,
        "uvIndex": 0,
        "ozone": 273.19
      },
      {
        "time": 1509940800,
        "summary": "Breezy and Overcast",
        "icon": "wind",
        "precipIntensity": 0.0204,
        "precipProbability": 0.29,
        "precipType": "rain",
        "temperature": 67.08,
        "apparentTemperature": 67.8,
        "dewPoint": 64.6,
        "humidity": 0.92,
        "pressure": 1009.56,
        "windSpeed": 18.59,
        "windGust": 38.42,
        "windBearing": 233,
        "cloudCover": 1,
        "uvIndex": 0,
        "ozone": 273.45
      },
      {
        "time": 1509944400,
        "summary": "Light Rain and Breezy",
        "icon": "rain",
        "precipIntensity": 0.0415,
        "precipProbability": 0.32,
        "precipType": "rain",
        "temperature": 66.65,
        "apparentTemperature": 67.21,
        "dewPoint": 63.34,
        "humidity": 0.89,
        "pressure": 1009.9,
        "windSpeed": 16.43,
        "windGust": 36.98,
        "windBearing": 251,
        "cloudCover": 1,
        "uvIndex": 0,
        "ozone": 273.73
      },
      {
        "time": 1509948000,
        "summary": "Rain",
        "icon": "rain",
        "precipIntensity": 0.0552,
        "precipProbability": 0.33,
        "precipType": "rain",
        "temperature": 66.09,
        "apparentTemperature": 66.44,
        "dewPoint": 61.81,
        "humidity": 0.86,
        "pressure": 1010.41,
        "windSpeed": 14.78,
        "windGust": 34.8,
        "windBearing": 241,
        "cloudCover": 1,
        "uvIndex": 0,
        "ozone": 274.81
      },
      {
        "time": 1509951600,
        "summary": "Light Rain",
        "icon": "rain",
        "precipIntensity": 0.0449,
        "precipProbability": 0.31,
        "precipType": "rain",
        "temperature": 65.18,
        "apparentTemperature": 65.32,
        "dewPoint": 60.03,
        "humidity": 0.83,
        "pressure": 1011.11,
        "windSpeed": 11.46,
        "windGust": 31.42,
        "windBearing": 177,
        "cloudCover": 0.96,
        "uvIndex": 0,
        "ozone": 277.49
      },
      {
        "time": 1509955200,
        "summary": "Mostly Cloudy",
        "icon": "partly-cloudy-night",
        "precipIntensity": 0.0256,
        "precipProbability": 0.28,
        "precipType": "rain",
        "temperature": 63.92,
        "apparentTemperature": 63.92,
        "dewPoint": 58.09,
        "humidity": 0.81,
        "pressure": 1011.97,
        "windSpeed": 11.17,
        "windGust": 27.35,
        "windBearing": 357,
        "cloudCover": 0.89,
        "uvIndex": 0,
        "ozone": 280.88
      },
      {
        "time": 1509958800,
        "summary": "Mostly Cloudy",
        "icon": "partly-cloudy-night",
        "precipIntensity": 0.0125,
        "precipProbability": 0.24,
        "precipType": "rain",
        "temperature": 62.41,
        "apparentTemperature": 62.41,
        "dewPoint": 56.3,
        "humidity": 0.8,
        "pressure": 1012.93,
        "windSpeed": 12.01,
        "windGust": 23.91,
        "windBearing": 292,
        "cloudCover": 0.83,
        "uvIndex": 0,
        "ozone": 283.17
      },
      {
        "time": 1509962400,
        "summary": "Mostly Cloudy",
        "icon": "partly-cloudy-night",
        "precipIntensity": 0.005,
        "precipProbability": 0.22,
        "precipType": "rain",
        "temperature": 60.56,
        "apparentTemperature": 60.56,
        "dewPoint": 54.73,
        "humidity": 0.81,
        "pressure": 1014.02,
        "windSpeed": 9.49,
        "windGust": 21.72,
        "windBearing": 263,
        "cloudCover": 0.8,
        "uvIndex": 0,
        "ozone": 283.2
      },
      {
        "time": 1509966000,
        "summary": "Mostly Cloudy",
        "icon": "partly-cloudy-night",
        "precipIntensity": 0.0009,
        "precipProbability": 0.19,
        "precipType": "rain",
        "temperature": 58.07,
        "apparentTemperature": 58.07,
        "dewPoint": 53.35,
        "humidity": 0.84,
        "pressure": 1015.2,
        "windSpeed": 7.99,
        "windGust": 20.17,
        "windBearing": 331,
        "cloudCover": 0.78,
        "uvIndex": 0,
        "ozone": 282.19
      },
      {
        "time": 1509969600,
        "summary": "Mostly Cloudy",
        "icon": "partly-cloudy-night",
        "precipIntensity": 0.0001,
        "precipProbability": 0.09,
        "precipType": "rain",
        "temperature": 56.09,
        "apparentTemperature": 56.09,
        "dewPoint": 52.18,
        "humidity": 0.87,
        "pressure": 1016.34,
        "windSpeed": 8.21,
        "windGust": 18.89,
        "windBearing": 331,
        "cloudCover": 0.7,
        "uvIndex": 0,
        "ozone": 281.07
      },
      {
        "time": 1509973200,
        "summary": "Partly Cloudy",
        "icon": "partly-cloudy-day",
        "precipIntensity": 0,
        "precipProbability": 0,
        "temperature": 55.15,
        "apparentTemperature": 55.15,
        "dewPoint": 51.25,
        "humidity": 0.87,
        "pressure": 1017.49,
        "windSpeed": 8.7,
        "windGust": 17.8,
        "windBearing": 335,
        "cloudCover": 0.51,
        "uvIndex": 0,
        "ozone": 280.31
      },
      {
        "time": 1509976800,
        "summary": "Partly Cloudy",
        "icon": "partly-cloudy-day",
        "precipIntensity": 0,
        "precipProbability": 0,
        "temperature": 55.04,
        "apparentTemperature": 55.04,
        "dewPoint": 50.52,
        "humidity": 0.85,
        "pressure": 1018.56,
        "windSpeed": 10.04,
        "windGust": 16.97,
        "windBearing": 347,
        "cloudCover": 0.28,
        "uvIndex": 1,
        "ozone": 279.57
      },
      {
        "time": 1509980400,
        "summary": "Clear",
        "icon": "clear-day",
        "precipIntensity": 0,
        "precipProbability": 0,
        "temperature": 55.1,
        "apparentTemperature": 55.1,
        "dewPoint": 49.99,
        "humidity": 0.83,
        "pressure": 1019.31,
        "windSpeed": 10.84,
        "windGust": 16.16,
        "windBearing": 359,
        "cloudCover": 0.12,
        "uvIndex": 1,
        "ozone": 278.51
      },
      {
        "time": 1509984000,
        "summary": "Clear",
        "icon": "clear-day",
        "precipIntensity": 0,
        "precipProbability": 0,
        "temperature": 55.55,
        "apparentTemperature": 55.55,
        "dewPoint": 49.69,
        "humidity": 0.81,
        "pressure": 1019.52,
        "windSpeed": 10.44,
        "windGust": 15.12,
        "windBearing": 8,
        "cloudCover": 0.07,
        "uvIndex": 2,
        "ozone": 276.74
      },
      {
        "time": 1509987600,
        "summary": "Clear",
        "icon": "clear-day",
        "precipIntensity": 0,
        "precipProbability": 0,
        "temperature": 56.13,
        "apparentTemperature": 56.13,
        "dewPoint": 49.58,
        "humidity": 0.79,
        "pressure": 1019.38,
        "windSpeed": 9.51,
        "windGust": 14.1,
        "windBearing": 16,
        "cloudCover": 0.07,
        "uvIndex": 3,
        "ozone": 274.6
      },
      {
        "time": 1509991200,
        "summary": "Clear",
        "icon": "clear-day",
        "precipIntensity": 0,
        "precipProbability": 0,
        "temperature": 56.66,
        "apparentTemperature": 56.66,
        "dewPoint": 49.45,
        "humidity": 0.77,
        "pressure": 1019.24,
        "windSpeed": 8.8,
        "windGust": 13.45,
        "windBearing": 25,
        "cloudCover": 0.1,
        "uvIndex": 3,
        "ozone": 272.94
      },
      {
        "time": 1509994800,
        "summary": "Clear",
        "icon": "clear-day",
        "precipIntensity": 0,
        "precipProbability": 0,
        "temperature": 56.67,
        "apparentTemperature": 56.67,
        "dewPoint": 49.22,
        "humidity": 0.76,
        "pressure": 1019.1,
        "windSpeed": 8.67,
        "windGust": 13.35,
        "windBearing": 34,
        "cloudCover": 0.18,
        "uvIndex": 2,
        "ozone": 271.9
      },
      {
        "time": 1509998400,
        "summary": "Partly Cloudy",
        "icon": "partly-cloudy-day",
        "precipIntensity": 0,
        "precipProbability": 0,
        "temperature": 56.34,
        "apparentTemperature": 56.34,
        "dewPoint": 48.97,
        "humidity": 0.76,
        "pressure": 1018.92,
        "windSpeed": 8.74,
        "windGust": 13.62,
        "windBearing": 44,
        "cloudCover": 0.29,
        "uvIndex": 1,
        "ozone": 271.23
      },
      {
        "time": 1510002000,
        "summary": "Partly Cloudy",
        "icon": "partly-cloudy-day",
        "precipIntensity": 0.0002,
        "precipProbability": 0.06,
        "precipType": "rain",
        "temperature": 55.7,
        "apparentTemperature": 55.7,
        "dewPoint": 48.72,
        "humidity": 0.77,
        "pressure": 1018.9,
        "windSpeed": 8.6,
        "windGust": 14.06,
        "windBearing": 52,
        "cloudCover": 0.39,
        "uvIndex": 1,
        "ozone": 270.88
      },
      {
        "time": 1510005600,
        "summary": "Partly Cloudy",
        "icon": "partly-cloudy-day",
        "precipIntensity": 0.0033,
        "precipProbability": 0.15,
        "precipType": "rain",
        "temperature": 55.03,
        "apparentTemperature": 55.03,
        "dewPoint": 48.51,
        "humidity": 0.79,
        "pressure": 1019.27,
        "windSpeed": 7.94,
        "windGust": 14.74,
        "windBearing": 59,
        "cloudCover": 0.48,
        "uvIndex": 0,
        "ozone": 270.96
      },
      {
        "time": 1510009200,
        "summary": "Partly Cloudy",
        "icon": "partly-cloudy-night",
        "precipIntensity": 0.0126,
        "precipProbability": 0.21,
        "precipType": "rain",
        "temperature": 54.09,
        "apparentTemperature": 54.09,
        "dewPoint": 48.29,
        "humidity": 0.81,
        "pressure": 1019.8,
        "windSpeed": 7.08,
        "windGust": 15.56,
        "windBearing": 64,
        "cloudCover": 0.55,
        "uvIndex": 0,
        "ozone": 271.37
      },
      {
        "time": 1510012800,
        "summary": "Mostly Cloudy",
        "icon": "partly-cloudy-night",
        "precipIntensity": 0.0196,
        "precipProbability": 0.26,
        "precipType": "rain",
        "temperature": 53.46,
        "apparentTemperature": 53.46,
        "dewPoint": 48.08,
        "humidity": 0.82,
        "pressure": 1020.05,
        "windSpeed": 6.65,
        "windGust": 16.03,
        "windBearing": 70,
        "cloudCover": 0.64,
        "uvIndex": 0,
        "ozone": 272.13
      },
      {
        "time": 1510016400,
        "summary": "Mostly Cloudy",
        "icon": "partly-cloudy-night",
        "precipIntensity": 0.0091,
        "precipProbability": 0.24,
        "precipType": "rain",
        "temperature": 53.09,
        "apparentTemperature": 53.09,
        "dewPoint": 47.88,
        "humidity": 0.82,
        "pressure": 1019.86,
        "windSpeed": 7.09,
        "windGust": 15.74,
        "windBearing": 77,
        "cloudCover": 0.77,
        "uvIndex": 0,
        "ozone": 273.57
      },
      {
        "time": 1510020000,
        "summary": "Mostly Cloudy",
        "icon": "partly-cloudy-night",
        "precipIntensity": 0.0008,
        "precipProbability": 0.2,
        "precipType": "rain",
        "temperature": 53.05,
        "apparentTemperature": 53.05,
        "dewPoint": 47.68,
        "humidity": 0.82,
        "pressure": 1019.41,
        "windSpeed": 7.93,
        "windGust": 15.09,
        "windBearing": 84,
        "cloudCover": 0.9,
        "uvIndex": 0,
        "ozone": 275.32
      },
      {
        "time": 1510023600,
        "summary": "Overcast",
        "icon": "cloudy",
        "precipIntensity": 0.0007,
        "precipProbability": 0.21,
        "precipType": "rain",
        "temperature": 53.28,
        "apparentTemperature": 53.28,
        "dewPoint": 47.64,
        "humidity": 0.81,
        "pressure": 1018.89,
        "windSpeed": 8.44,
        "windGust": 14.86,
        "windBearing": 92,
        "cloudCover": 1,
        "uvIndex": 0,
        "ozone": 276.15
      },
      {
        "time": 1510027200,
        "summary": "Overcast",
        "icon": "cloudy",
        "precipIntensity": 0.0267,
        "precipProbability": 0.31,
        "precipType": "rain",
        "temperature": 53.96,
        "apparentTemperature": 53.96,
        "dewPoint": 47.83,
        "humidity": 0.8,
        "pressure": 1018.35,
        "windSpeed": 8.38,
        "windGust": 15.52,
        "windBearing": 103,
        "cloudCover": 1,
        "uvIndex": 0,
        "ozone": 274.99
      },
      {
        "time": 1510030800,
        "summary": "Rain",
        "icon": "rain",
        "precipIntensity": 0.1413,
        "precipProbability": 0.49,
        "precipType": "rain",
        "temperature": 54.83,
        "apparentTemperature": 54.83,
        "dewPoint": 48.17,
        "humidity": 0.78,
        "pressure": 1017.76,
        "windSpeed": 8.05,
        "windGust": 16.59,
        "windBearing": 116,
        "cloudCover": 1,
        "uvIndex": 0,
        "ozone": 272.91
      },
      {
        "time": 1510034400,
        "summary": "Heavy Rain",
        "icon": "rain",
        "precipIntensity": 0.2421,
        "precipProbability": 0.58,
        "precipType": "rain",
        "temperature": 55.73,
        "apparentTemperature": 55.73,
        "dewPoint": 48.6,
        "humidity": 0.77,
        "pressure": 1017.19,
        "windSpeed": 7.65,
        "windGust": 17.4,
        "windBearing": 125,
        "cloudCover": 1,
        "uvIndex": 0,
        "ozone": 271.28
      },
      {
        "time": 1510038000,
        "summary": "Rain",
        "icon": "rain",
        "precipIntensity": 0.1706,
        "precipProbability": 0.53,
        "precipType": "rain",
        "temperature": 56.4,
        "apparentTemperature": 56.4,
        "dewPoint": 49.14,
        "humidity": 0.77,
        "pressure": 1016.59,
        "windSpeed": 7.03,
        "windGust": 17.53,
        "windBearing": 129,
        "cloudCover": 1,
        "uvIndex": 0,
        "ozone": 270.64
      },
      {
        "time": 1510041600,
        "summary": "Rain",
        "icon": "rain",
        "precipIntensity": 0.0591,
        "precipProbability": 0.41,
        "precipType": "rain",
        "temperature": 56.76,
        "apparentTemperature": 56.76,
        "dewPoint": 49.75,
        "humidity": 0.77,
        "pressure": 1016.02,
        "windSpeed": 6.28,
        "windGust": 17.4,
        "windBearing": 131,
        "cloudCover": 1,
        "uvIndex": 0,
        "ozone": 270.5
      },
      {
        "time": 1510045200,
        "summary": "Overcast",
        "icon": "cloudy",
        "precipIntensity": 0.016,
        "precipProbability": 0.33,
        "precipType": "rain",
        "temperature": 56.87,
        "apparentTemperature": 56.87,
        "dewPoint": 50.28,
        "humidity": 0.79,
        "pressure": 1015.54,
        "windSpeed": 6.03,
        "windGust": 17.43,
        "windBearing": 133,
        "cloudCover": 1,
        "uvIndex": 0,
        "ozone": 270.36
      },
      {
        "time": 1510048800,
        "summary": "Overcast",
        "icon": "cloudy",
        "precipIntensity": 0.0106,
        "precipProbability": 0.31,
        "precipType": "rain",
        "temperature": 56.76,
        "apparentTemperature": 56.76,
        "dewPoint": 50.67,
        "humidity": 0.8,
        "pressure": 1015.24,
        "windSpeed": 6.78,
        "windGust": 17.78,
        "windBearing": 138,
        "cloudCover": 1,
        "uvIndex": 0,
        "ozone": 270.07
      },
      {
        "time": 1510052400,
        "summary": "Overcast",
        "icon": "cloudy",
        "precipIntensity": 0.0119,
        "precipProbability": 0.3,
        "precipType": "rain",
        "temperature": 56.61,
        "apparentTemperature": 56.61,
        "dewPoint": 50.99,
        "humidity": 0.81,
        "pressure": 1015.05,
        "windSpeed": 8.01,
        "windGust": 18.25,
        "windBearing": 120,
        "cloudCover": 1,
        "uvIndex": 0,
        "ozone": 269.72
      },
      {
        "time": 1510056000,
        "summary": "Overcast",
        "icon": "cloudy",
        "precipIntensity": 0.014,
        "precipProbability": 0.28,
        "precipType": "rain",
        "temperature": 56.66,
        "apparentTemperature": 56.66,
        "dewPoint": 51.31,
        "humidity": 0.82,
        "pressure": 1014.9,
        "windSpeed": 8.85,
        "windGust": 18.93,
        "windBearing": 126,
        "cloudCover": 1,
        "uvIndex": 0,
        "ozone": 269.73
      },
      {
        "time": 1510059600,
        "summary": "Overcast",
        "icon": "cloudy",
        "precipIntensity": 0.013,
        "precipProbability": 0.25,
        "precipType": "rain",
        "temperature": 57.25,
        "apparentTemperature": 57.25,
        "dewPoint": 51.62,
        "humidity": 0.81,
        "pressure": 1014.85,
        "windSpeed": 9.65,
        "windGust": 20.25,
        "windBearing": 99,
        "cloudCover": 1,
        "uvIndex": 0,
        "ozone": 270.1
      },
      {
        "time": 1510063200,
        "summary": "Overcast",
        "icon": "cloudy",
        "precipIntensity": 0.0104,
        "precipProbability": 0.21,
        "precipType": "rain",
        "temperature": 58.04,
        "apparentTemperature": 58.04,
        "dewPoint": 51.94,
        "humidity": 0.8,
        "pressure": 1014.85,
        "windSpeed": 10.06,
        "windGust": 21.77,
        "windBearing": 38,
        "cloudCover": 1,
        "uvIndex": 0,
        "ozone": 270.88
      },
      {
        "time": 1510066800,
        "summary": "Overcast",
        "icon": "cloudy",
        "precipIntensity": 0.0082,
        "precipProbability": 0.19,
        "precipType": "rain",
        "temperature": 58.79,
        "apparentTemperature": 58.79,
        "dewPoint": 52.39,
        "humidity": 0.79,
        "pressure": 1014.65,
        "windSpeed": 10.31,
        "windGust": 22.18,
        "windBearing": 39,
        "cloudCover": 0.99,
        "uvIndex": 1,
        "ozone": 271.61
      },
      {
        "time": 1510070400,
        "summary": "Overcast",
        "icon": "cloudy",
        "precipIntensity": 0.0067,
        "precipProbability": 0.19,
        "precipType": "rain",
        "temperature": 59.42,
        "apparentTemperature": 59.42,
        "dewPoint": 53.25,
        "humidity": 0.8,
        "pressure": 1014.07,
        "windSpeed": 10.01,
        "windGust": 20.42,
        "windBearing": 53,
        "cloudCover": 0.98,
        "uvIndex": 1,
        "ozone": 272.24
      },
      {
        "time": 1510074000,
        "summary": "Overcast",
        "icon": "cloudy",
        "precipIntensity": 0.0054,
        "precipProbability": 0.2,
        "precipType": "rain",
        "temperature": 60.02,
        "apparentTemperature": 60.02,
        "dewPoint": 54.19,
        "humidity": 0.81,
        "pressure": 1013.3,
        "windSpeed": 9.63,
        "windGust": 17.57,
        "windBearing": 132,
        "cloudCover": 0.96,
        "uvIndex": 2,
        "ozone": 272.89
      },
      {
        "time": 1510077600,
        "summary": "Overcast",
        "icon": "cloudy",
        "precipIntensity": 0.0054,
        "precipProbability": 0.24,
        "precipType": "rain",
        "temperature": 60.12,
        "apparentTemperature": 60.12,
        "dewPoint": 54.62,
        "humidity": 0.82,
        "pressure": 1012.62,
        "windSpeed": 9.56,
        "windGust": 15.6,
        "windBearing": 180,
        "cloudCover": 0.95,
        "uvIndex": 2,
        "ozone": 273.52
      },
      {
        "time": 1510081200,
        "summary": "Overcast",
        "icon": "cloudy",
        "precipIntensity": 0.0093,
        "precipProbability": 0.32,
        "precipType": "rain",
        "temperature": 59.46,
        "apparentTemperature": 59.46,
        "dewPoint": 54.32,
        "humidity": 0.83,
        "pressure": 1012.11,
        "windSpeed": 9.49,
        "windGust": 15.29,
        "windBearing": 146,
        "cloudCover": 0.96,
        "uvIndex": 1,
        "ozone": 273.87
      },
      {
        "time": 1510084800,
        "summary": "Overcast",
        "icon": "cloudy",
        "precipIntensity": 0.0215,
        "precipProbability": 0.44,
        "precipType": "rain",
        "temperature": 58.15,
        "apparentTemperature": 58.15,
        "dewPoint": 53.54,
        "humidity": 0.85,
        "pressure": 1011.71,
        "windSpeed": 9.68,
        "windGust": 15.87,
        "windBearing": 27,
        "cloudCover": 0.98,
        "uvIndex": 1,
        "ozone": 274.12
      },
      {
        "time": 1510088400,
        "summary": "Overcast",
        "icon": "cloudy",
        "precipIntensity": 0.0327,
        "precipProbability": 0.53,
        "precipType": "rain",
        "temperature": 56.92,
        "apparentTemperature": 56.92,
        "dewPoint": 52.53,
        "humidity": 0.85,
        "pressure": 1011.58,
        "windSpeed": 11.16,
        "windGust": 16.95,
        "windBearing": 346,
        "cloudCover": 0.99,
        "uvIndex": 0,
        "ozone": 274.48
      },
      {
        "time": 1510092000,
        "summary": "Overcast",
        "icon": "cloudy",
        "precipIntensity": 0.032,
        "precipProbability": 0.55,
        "precipType": "rain",
        "temperature": 55.71,
        "apparentTemperature": 55.71,
        "dewPoint": 51.31,
        "humidity": 0.85,
        "pressure": 1011.82,
        "windSpeed": 7.38,
        "windGust": 18.71,
        "windBearing": 21,
        "cloudCover": 1,
        "uvIndex": 0,
        "ozone": 274.83
      },
      {
        "time": 1510095600,
        "summary": "Overcast",
        "icon": "cloudy",
        "precipIntensity": 0.032,
        "precipProbability": 0.55,
        "precipType": "rain",
        "temperature": 54.51,
        "apparentTemperature": 54.51,
        "dewPoint": 49.81,
        "humidity": 0.84,
        "pressure": 1012.31,
        "windSpeed": 11.22,
        "windGust": 20.95,
        "windBearing": 12,
        "cloudCover": 1,
        "uvIndex": 0,
        "ozone": 275.32
      },
      {
        "time": 1510099200,
        "summary": "Overcast",
        "icon": "cloudy",
        "precipIntensity": 0.0341,
        "precipProbability": 0.53,
        "precipType": "rain",
        "temperature": 53.14,
        "apparentTemperature": 53.14,
        "dewPoint": 48.14,
        "humidity": 0.83,
        "pressure": 1012.9,
        "windSpeed": 12.85,
        "windGust": 22.76,
        "windBearing": 2,
        "cloudCover": 1,
        "uvIndex": 0,
        "ozone": 276.35
      },
      {
        "time": 1510102800,
        "summary": "Overcast",
        "icon": "cloudy",
        "precipIntensity": 0.0267,
        "precipProbability": 0.48,
        "precipType": "rain",
        "temperature": 51.51,
        "apparentTemperature": 51.51,
        "dewPoint": 46.19,
        "humidity": 0.82,
        "pressure": 1013.53,
        "windSpeed": 13.25,
        "windGust": 23.65,
        "windBearing": 2,
        "cloudCover": 1,
        "uvIndex": 0,
        "ozone": 278.28
      },
      {
        "time": 1510106400,
        "summary": "Overcast",
        "icon": "cloudy",
        "precipIntensity": 0.0153,
        "precipProbability": 0.4,
        "precipType": "rain",
        "temperature": 49.7,
        "apparentTemperature": 44.56,
        "dewPoint": 44.11,
        "humidity": 0.81,
        "pressure": 1014.25,
        "windSpeed": 13.75,
        "windGust": 24.07,
        "windBearing": 7,
        "cloudCover": 1,
        "uvIndex": 0,
        "ozone": 280.72
      },
      {
        "time": 1510110000,
        "summary": "Overcast",
        "icon": "cloudy",
        "precipIntensity": 0.0079,
        "precipProbability": 0.35,
        "precipType": "rain",
        "temperature": 48.02,
        "apparentTemperature": 42.38,
        "dewPoint": 42.21,
        "humidity": 0.8,
        "pressure": 1014.99,
        "windSpeed": 13.94,
        "windGust": 24.51,
        "windBearing": 10,
        "cloudCover": 1,
        "uvIndex": 0,
        "ozone": 283.31
      },
      {
        "time": 1510113600,
        "summary": "Overcast",
        "icon": "cloudy",
        "precipIntensity": 0.0041,
        "precipProbability": 0.3,
        "precipType": "rain",
        "temperature": 46.58,
        "apparentTemperature": 40.63,
        "dewPoint": 40.61,
        "humidity": 0.8,
        "pressure": 1015.77,
        "windSpeed": 13.67,
        "windGust": 25.02,
        "windBearing": 9,
        "cloudCover": 0.99,
        "uvIndex": 0,
        "ozone": 285.98
      },
      {
        "time": 1510117200,
        "summary": "Overcast",
        "icon": "cloudy",
        "precipIntensity": 0.0018,
        "precipProbability": 0.26,
        "precipType": "rain",
        "temperature": 45.47,
        "apparentTemperature": 39.38,
        "dewPoint": 39.23,
        "humidity": 0.79,
        "pressure": 1016.61,
        "windSpeed": 13.1,
        "windGust": 25.52,
        "windBearing": 5,
        "cloudCover": 0.99,
        "uvIndex": 0,
        "ozone": 288.74
      },
      {
        "time": 1510120800,
        "summary": "Overcast",
        "icon": "cloudy",
        "precipIntensity": 0.001,
        "precipProbability": 0.23,
        "precipType": "rain",
        "temperature": 44.82,
        "apparentTemperature": 38.69,
        "dewPoint": 38.15,
        "humidity": 0.77,
        "pressure": 1017.4,
        "windSpeed": 12.68,
        "windGust": 26.18,
        "windBearing": 3,
        "cloudCover": 0.98,
        "uvIndex": 0,
        "ozone": 291.04
      },
      {
        "time": 1510124400,
        "summary": "Overcast",
        "icon": "cloudy",
        "precipIntensity": 0.0012,
        "precipProbability": 0.21,
        "precipType": "rain",
        "temperature": 44.67,
        "apparentTemperature": 38.56,
        "dewPoint": 37.57,
        "humidity": 0.76,
        "pressure": 1018.13,
        "windSpeed": 12.52,
        "windGust": 27.13,
        "windBearing": 0,
        "cloudCover": 0.99,
        "uvIndex": 0,
        "ozone": 292.38
      },
      {
        "time": 1510128000,
        "summary": "Overcast",
        "icon": "cloudy",
        "precipIntensity": 0.002,
        "precipProbability": 0.21,
        "precipType": "rain",
        "temperature": 44.66,
        "apparentTemperature": 38.54,
        "dewPoint": 37.31,
        "humidity": 0.75,
        "pressure": 1018.86,
        "windSpeed": 12.49,
        "windGust": 28.24,
        "windBearing": 358,
        "cloudCover": 0.99,
        "uvIndex": 0,
        "ozone": 293.26
      },
      {
        "time": 1510131600,
        "summary": "Overcast",
        "icon": "cloudy",
        "precipIntensity": 0.0027,
        "precipProbability": 0.2,
        "precipType": "rain",
        "temperature": 44.41,
        "apparentTemperature": 38.18,
        "dewPoint": 37,
        "humidity": 0.75,
        "pressure": 1019.55,
        "windSpeed": 12.65,
        "windGust": 29.11,
        "windBearing": 357,
        "cloudCover": 0.99,
        "uvIndex": 0,
        "ozone": 294.58
      },
      {
        "time": 1510135200,
        "summary": "Overcast",
        "icon": "cloudy",
        "precipIntensity": 0.0023,
        "precipProbability": 0.2,
        "precipType": "rain",
        "temperature": 43.79,
        "apparentTemperature": 37.24,
        "dewPoint": 36.41,
        "humidity": 0.75,
        "pressure": 1020.24,
        "windSpeed": 13.14,
        "windGust": 29.68,
        "windBearing": 356,
        "cloudCover": 1,
        "uvIndex": 0,
        "ozone": 297.06
      },
      {
        "time": 1510138800,
        "summary": "Overcast",
        "icon": "cloudy",
        "precipIntensity": 0.0017,
        "precipProbability": 0.19,
        "precipType": "rain",
        "temperature": 43.05,
        "apparentTemperature": 36.09,
        "dewPoint": 35.74,
        "humidity": 0.75,
        "pressure": 1020.88,
        "windSpeed": 13.83,
        "windGust": 30.02,
        "windBearing": 356,
        "cloudCover": 1,
        "uvIndex": 0,
        "ozone": 300
      },
      {
        "time": 1510142400,
        "summary": "Overcast",
        "icon": "cloudy",
        "precipIntensity": 0.0013,
        "precipProbability": 0.17,
        "precipType": "rain",
        "temperature": 42.23,
        "apparentTemperature": 34.91,
        "dewPoint": 35.33,
        "humidity": 0.76,
        "pressure": 1021.56,
        "windSpeed": 14.28,
        "windGust": 30.12,
        "windBearing": 354,
        "cloudCover": 1,
        "uvIndex": 0,
        "ozone": 302.37
      },
      {
        "time": 1510146000,
        "summary": "Overcast",
        "icon": "cloudy",
        "precipIntensity": 0.001,
        "precipProbability": 0.17,
        "precipType": "rain",
        "temperature": 41.48,
        "apparentTemperature": 33.95,
        "dewPoint": 35.3,
        "humidity": 0.78,
        "pressure": 1022.37,
        "windSpeed": 14.29,
        "windGust": 29.96,
        "windBearing": 354,
        "cloudCover": 1,
        "uvIndex": 0,
        "ozone": 303.65
      },
      {
        "time": 1510149600,
        "summary": "Overcast",
        "icon": "cloudy",
        "precipIntensity": 0.0009,
        "precipProbability": 0.17,
        "precipType": "rain",
        "temperature": 40.8,
        "apparentTemperature": 33.14,
        "dewPoint": 35.54,
        "humidity": 0.81,
        "pressure": 1023.23,
        "windSpeed": 14.08,
        "windGust": 29.51,
        "windBearing": 354,
        "cloudCover": 1,
        "uvIndex": 0,
        "ozone": 304.26
      },
      {
        "time": 1510153200,
        "summary": "Overcast",
        "icon": "cloudy",
        "precipIntensity": 0.0008,
        "precipProbability": 0.17,
        "precipType": "rain",
        "temperature": 40.53,
        "apparentTemperature": 32.93,
        "dewPoint": 35.73,
        "humidity": 0.83,
        "pressure": 1023.83,
        "windSpeed": 13.68,
        "windGust": 28.73,
        "windBearing": 353,
        "cloudCover": 1,
        "uvIndex": 1,
        "ozone": 304.66
      },
      {
        "time": 1510156800,
        "summary": "Overcast",
        "icon": "cloudy",
        "precipIntensity": 0.0007,
        "precipProbability": 0.17,
        "precipType": "rain",
        "temperature": 40.94,
        "apparentTemperature": 33.67,
        "dewPoint": 35.82,
        "humidity": 0.82,
        "pressure": 1024.01,
        "windSpeed": 13.04,
        "windGust": 27.42,
        "windBearing": 352,
        "cloudCover": 1,
        "uvIndex": 1,
        "ozone": 304.89
      },
      {
        "time": 1510160400,
        "summary": "Overcast",
        "icon": "cloudy",
        "precipIntensity": 0.0005,
        "precipProbability": 0.16,
        "precipType": "rain",
        "temperature": 41.81,
        "apparentTemperature": 35.05,
        "dewPoint": 35.9,
        "humidity": 0.79,
        "pressure": 1023.97,
        "windSpeed": 12.21,
        "windGust": 25.77,
        "windBearing": 350,
        "cloudCover": 1,
        "uvIndex": 1,
        "ozone": 304.89
      },
      {
        "time": 1510164000,
        "summary": "Overcast",
        "icon": "cloudy",
        "precipIntensity": 0.0004,
        "precipProbability": 0.15,
        "precipType": "rain",
        "temperature": 42.74,
        "apparentTemperature": 36.47,
        "dewPoint": 35.83,
        "humidity": 0.76,
        "pressure": 1023.9,
        "windSpeed": 11.5,
        "windGust": 24.35,
        "windBearing": 349,
        "cloudCover": 1,
        "uvIndex": 1,
        "ozone": 304.33
      },
      {
        "time": 1510167600,
        "summary": "Overcast",
        "icon": "cloudy",
        "precipIntensity": 0.0002,
        "precipProbability": 0.12,
        "precipType": "rain",
        "temperature": 43.55,
        "apparentTemperature": 37.64,
        "dewPoint": 35.64,
        "humidity": 0.73,
        "pressure": 1023.85,
        "windSpeed": 11.05,
        "windGust": 23.25,
        "windBearing": 347,
        "cloudCover": 0.97,
        "uvIndex": 1,
        "ozone": 303.06
      },
      {
        "time": 1510171200,
        "summary": "Mostly Cloudy",
        "icon": "partly-cloudy-day",
        "precipIntensity": 0,
        "precipProbability": 0,
        "temperature": 43.92,
        "apparentTemperature": 38.24,
        "dewPoint": 35.36,
        "humidity": 0.72,
        "pressure": 1023.79,
        "windSpeed": 10.71,
        "windGust": 22.33,
        "windBearing": 346,
        "cloudCover": 0.93,
        "uvIndex": 1,
        "ozone": 301.32
      },
      {
        "time": 1510174800,
        "summary": "Mostly Cloudy",
        "icon": "partly-cloudy-day",
        "precipIntensity": 0,
        "precipProbability": 0,
        "temperature": 43.5,
        "apparentTemperature": 37.86,
        "dewPoint": 34.98,
        "humidity": 0.72,
        "pressure": 1023.9,
        "windSpeed": 10.31,
        "windGust": 21.85,
        "windBearing": 346,
        "cloudCover": 0.87,
        "uvIndex": 0,
        "ozone": 299.25
      },
      {
        "time": 1510178400,
        "summary": "Mostly Cloudy",
        "icon": "partly-cloudy-day",
        "precipIntensity": 0,
        "precipProbability": 0,
        "temperature": 42.34,
        "apparentTemperature": 36.65,
        "dewPoint": 34.54,
        "humidity": 0.74,
        "pressure": 1024.4,
        "windSpeed": 9.72,
        "windGust": 22.15,
        "windBearing": 348,
        "cloudCover": 0.77,
        "uvIndex": 0,
        "ozone": 296.69
      },
      {
        "time": 1510182000,
        "summary": "Overcast",
        "icon": "cloudy",
        "precipIntensity": 0.0007,
        "precipProbability": 0.21,
        "precipType": "rain",
        "temperature": 42.52,
        "apparentTemperature": 36.36,
        "dewPoint": 37.95,
        "humidity": 0.84,
        "pressure": 1021.8,
        "windSpeed": 11.04,
        "windGust": 25.51,
        "windBearing": 356,
        "cloudCover": 0.96,
        "uvIndex": 0,
        "ozone": 302.82
      },
      {
        "time": 1510185600,
        "summary": "Overcast",
        "icon": "cloudy",
        "precipIntensity": 0.0006,
        "precipProbability": 0.19,
        "precipType": "rain",
        "temperature": 41.55,
        "apparentTemperature": 35.09,
        "dewPoint": 37.54,
        "humidity": 0.86,
        "pressure": 1022.3,
        "windSpeed": 11.19,
        "windGust": 26.23,
        "windBearing": 358,
        "cloudCover": 0.95,
        "uvIndex": 0,
        "ozone": 303.03
      }
    ]
  },
  "daily": {
    "summary": "Rain today through Tuesday, with temperatures peaking at 68F on Sunday.",
    "icon": "rain",
    "data": [
      {
        "time": 1509508800,
        "summary": "Rain starting in the evening and breezy overnight.",
        "icon": "rain",
        "sunriseTime": 1509538509,
        "sunsetTime": 1509576210,
        "moonPhase": 0.41,
        "precipIntensity": 0.0183,
        "precipIntensityMax": 0.1048,
        "precipIntensityMaxTime": 1509580800,
        "precipProbability": 1.00,
        "precipType": "rain",
        "temperatureHigh": 43.59,
        "temperatureHighTime": 1509570000,
        "temperatureLow": 43.21,
        "temperatureLowTime": 1509577200,
        "apparentTemperatureHigh": 43.59,
        "apparentTemperatureHighTime": 1509570000,
        "apparentTemperatureLow": 43.21,
        "apparentTemperatureLowTime": 1509577200,
        "dewPoint": 36.99,
        "humidity": 0.9,
        "pressure": 1017.23,
        "windSpeed": 2.11,
        "windGust": 27.76,
        "windGustTime": 1509591600,
        "windBearing": 161,
        "cloudCover": 0.23,
        "uvIndex": 2,
        "uvIndexTime": 1509555600,
        "visibility": 6.67,
        "ozone": 296.46,
        "temperatureMin": 34,
        "temperatureMinTime": 1509534000,
        "temperatureMax": 51.19,
        "temperatureMaxTime": 1509591600,
        "apparentTemperatureMin": 34,
        "apparentTemperatureMinTime": 1509534000,
        "apparentTemperatureMax": 51.19,
        "apparentTemperatureMaxTime": 1509591600
      },
      {
        "time": 1509595200,
        "summary": "Breezy in the morning and light rain starting in the evening.",
        "icon": "rain",
        "sunriseTime": 1509624979,
        "sunsetTime": 1509662540,
        "moonPhase": 0.44,
        "precipIntensity": 0.013,
        "precipIntensityMax": 0.0455,
        "precipIntensityMaxTime": 1509678000,
        "precipProbability": 0.94,
        "precipType": "rain",
        "temperatureHigh": 63.58,
        "temperatureHighTime": 1509660000,
        "temperatureLow": 52.57,
        "temperatureLowTime": 1509710400,
        "apparentTemperatureHigh": 63.88,
        "apparentTemperatureHighTime": 1509660000,
        "apparentTemperatureLow": 52.57,
        "apparentTemperatureLowTime": 1509710400,
        "dewPoint": 57.98,
        "humidity": 0.91,
        "pressure": 1012.33,
        "windSpeed": 14.96,
        "windGust": 39.62,
        "windGustTime": 1509602400,
        "windBearing": 191,
        "cloudCover": 0.96,
        "uvIndex": 2,
        "uvIndexTime": 1509642000,
        "visibility": 10,
        "ozone": 286.21,
        "temperatureMin": 53.69,
        "temperatureMinTime": 1509595200,
        "temperatureMax": 65.38,
        "temperatureMaxTime": 1509678000,
        "apparentTemperatureMin": 53.69,
        "apparentTemperatureMinTime": 1509595200,
        "apparentTemperatureMax": 65.8,
        "apparentTemperatureMaxTime": 1509678000
      },
      {
        "time": 1509681600,
        "summary": "Mostly cloudy until afternoon.",
        "icon": "partly-cloudy-day",
        "sunriseTime": 1509711448,
        "sunsetTime": 1509748872,
        "moonPhase": 0.47,
        "precipIntensity": 0.0041,
        "precipIntensityMax": 0.0322,
        "precipIntensityMaxTime": 1509681600,
        "precipProbability": 0.57,
        "precipType": "rain",
        "temperatureHigh": 56.11,
        "temperatureHighTime": 1509739200,
        "temperatureLow": 42.14,
        "temperatureLowTime": 1509793200,
        "apparentTemperatureHigh": 56.11,
        "apparentTemperatureHighTime": 1509739200,
        "apparentTemperatureLow": 36.82,
        "apparentTemperatureLowTime": 1509793200,
        "dewPoint": 48.84,
        "humidity": 0.8,
        "pressure": 1020.2,
        "windSpeed": 7.08,
        "windGust": 23.59,
        "windGustTime": 1509681600,
        "windBearing": 13,
        "cloudCover": 0.52,
        "uvIndex": 2,
        "uvIndexTime": 1509724800,
        "visibility": 10,
        "ozone": 261.69,
        "temperatureMin": 45.57,
        "temperatureMinTime": 1509764400,
        "temperatureMax": 65.42,
        "temperatureMaxTime": 1509681600,
        "apparentTemperatureMin": 40.98,
        "apparentTemperatureMinTime": 1509764400,
        "apparentTemperatureMax": 65.86,
        "apparentTemperatureMaxTime": 1509681600
      },
      {
        "time": 1509768000,
        "summary": "Mostly cloudy throughout the day.",
        "icon": "partly-cloudy-day",
        "sunriseTime": 1509797918,
        "sunsetTime": 1509835206,
        "moonPhase": 0.52,
        "precipIntensity": 0.0007,
        "precipIntensityMax": 0.0025,
        "precipIntensityMaxTime": 1509850800,
        "precipProbability": 0.18,
        "precipType": "rain",
        "temperatureHigh": 56.22,
        "temperatureHighTime": 1509829200,
        "temperatureLow": 55.51,
        "temperatureLowTime": 1509840000,
        "apparentTemperatureHigh": 56.22,
        "apparentTemperatureHighTime": 1509829200,
        "apparentTemperatureLow": 55.51,
        "apparentTemperatureLowTime": 1509840000,
        "dewPoint": 44.71,
        "humidity": 0.84,
        "pressure": 1020.19,
        "windSpeed": 8.84,
        "windGust": 22.44,
        "windGustTime": 1509850800,
        "windBearing": 128,
        "cloudCover": 0.62,
        "uvIndex": 2,
        "uvIndexTime": 1509814800,
        "visibility": 10,
        "ozone": 267.18,
        "temperatureMin": 42.14,
        "temperatureMinTime": 1509793200,
        "temperatureMax": 57.02,
        "temperatureMaxTime": 1509850800,
        "apparentTemperatureMin": 36.82,
        "apparentTemperatureMinTime": 1509793200,
        "apparentTemperatureMax": 57.02,
        "apparentTemperatureMaxTime": 1509850800
      },
      {
        "time": 1509854400,
        "summary": "Breezy starting in the evening and rain overnight.",
        "icon": "rain",
        "sunriseTime": 1509884387,
        "sunsetTime": 1509921541,
        "moonPhase": 0.55,
        "precipIntensity": 0.0066,
        "precipIntensityMax": 0.0204,
        "precipIntensityMaxTime": 1509940800,
        "precipProbability": 0.57,
        "precipType": "rain",
        "temperatureHigh": 67.81,
        "temperatureHighTime": 1509926400,
        "temperatureLow": 55.15,
        "temperatureLowTime": 1509973200,
        "apparentTemperatureHigh": 68.62,
        "apparentTemperatureHighTime": 1509926400,
        "apparentTemperatureLow": 55.15,
        "apparentTemperatureLowTime": 1509973200,
        "dewPoint": 62.06,
        "humidity": 0.92,
        "pressure": 1011.21,
        "windSpeed": 13.55,
        "windGust": 39.42,
        "windGustTime": 1509933600,
        "windBearing": 200,
        "cloudCover": 0.98,
        "uvIndex": 2,
        "uvIndexTime": 1509901200,
        "ozone": 271.72,
        "temperatureMin": 57.55,
        "temperatureMinTime": 1509854400,
        "temperatureMax": 67.92,
        "temperatureMaxTime": 1509930000,
        "apparentTemperatureMin": 57.55,
        "apparentTemperatureMinTime": 1509854400,
        "apparentTemperatureMax": 68.74,
        "apparentTemperatureMaxTime": 1509930000
      },
      {
        "time": 1509944400,
        "summary": "Heavy rain overnight.",
        "icon": "rain",
        "sunriseTime": 1509970857,
        "sunsetTime": 1510007877,
        "moonPhase": 0.59,
        "precipIntensity": 0.0108,
        "precipIntensityMax": 0.0552,
        "precipIntensityMaxTime": 1509948000,
        "precipProbability": 0.64,
        "precipType": "rain",
        "temperatureHigh": 56.67,
        "temperatureHighTime": 1509994800,
        "temperatureLow": 53.05,
        "temperatureLowTime": 1510020000,
        "apparentTemperatureHigh": 56.67,
        "apparentTemperatureHighTime": 1509994800,
        "apparentTemperatureLow": 53.05,
        "apparentTemperatureLowTime": 1510020000,
        "dewPoint": 51.8,
        "humidity": 0.82,
        "pressure": 1017,
        "windSpeed": 3.74,
        "windGust": 36.98,
        "windGustTime": 1509944400,
        "windBearing": 8,
        "cloudCover": 0.6,
        "uvIndex": 3,
        "uvIndexTime": 1509987600,
        "ozone": 276.15,
        "temperatureMin": 53.05,
        "temperatureMinTime": 1510020000,
        "temperatureMax": 66.65,
        "temperatureMaxTime": 1509944400,
        "apparentTemperatureMin": 53.05,
        "apparentTemperatureMinTime": 1510020000,
        "apparentTemperatureMax": 67.21,
        "apparentTemperatureMaxTime": 1509944400
      },
      {
        "time": 1510030800,
        "summary": "Overcast throughout the day.",
        "icon": "cloudy",
        "sunriseTime": 1510057328,
        "sunsetTime": 1510094216,
        "moonPhase": 0.63,
        "precipIntensity": 0.0388,
        "precipIntensityMax": 0.2421,
        "precipIntensityMaxTime": 1510034400,
        "precipProbability": 0.9,
        "precipType": "rain",
        "temperatureHigh": 60.12,
        "temperatureHighTime": 1510077600,
        "temperatureLow": 41.48,
        "temperatureLowTime": 1510146000,
        "apparentTemperatureHigh": 60.12,
        "apparentTemperatureHighTime": 1510077600,
        "apparentTemperatureLow": 33.95,
        "apparentTemperatureLowTime": 1510146000,
        "dewPoint": 49.99,
        "humidity": 0.81,
        "pressure": 1014.32,
        "windSpeed": 5.1,
        "windGust": 25.02,
        "windGustTime": 1510113600,
        "windBearing": 57,
        "cloudCover": 1.00,
        "uvIndex": 2,
        "uvIndexTime": 1510074000,
        "ozone": 273.9,
        "temperatureMin": 46.58,
        "temperatureMinTime": 1510113600,
        "temperatureMax": 60.12,
        "temperatureMaxTime": 1510077600,
        "apparentTemperatureMin": 40.63,
        "apparentTemperatureMinTime": 1510113600,
        "apparentTemperatureMax": 60.12,
        "apparentTemperatureMaxTime": 1510077600
      },
      {
        "time": 1510117200,
        "summary": "Mostly cloudy throughout the day.",
        "icon": "partly-cloudy-day",
        "sunriseTime": 1510143798,
        "sunsetTime": 1510180555,
        "moonPhase": 0.67,
        "precipIntensity": 0.0009,
        "precipIntensityMax": 0.0027,
        "precipIntensityMaxTime": 1510131600,
        "precipProbability": 0.35,
        "precipType": "rain",
        "temperatureHigh": 43.92,
        "temperatureHighTime": 1510171200,
        "temperatureLow": 33.21,
        "temperatureLowTime": 1510225200,
        "apparentTemperatureHigh": 38.24,
        "apparentTemperatureHighTime": 1510171200,
        "apparentTemperatureLow": 27.28,
        "apparentTemperatureLowTime": 1510221600,
        "dewPoint": 36.27,
        "humidity": 0.79,
        "pressure": 1021.95,
        "windSpeed": 11.83,
        "windGust": 30.12,
        "windGustTime": 1510142400,
        "windBearing": 356,
        "cloudCover": 0.93,
        "uvIndex": 1,
        "uvIndexTime": 1510153200,
        "ozone": 298.86,
        "temperatureMin": 37.19,
        "temperatureMinTime": 1510200000,
        "temperatureMax": 45.47,
        "temperatureMaxTime": 1510117200,
        "apparentTemperatureMin": 31.05,
        "apparentTemperatureMinTime": 1510200000,
        "apparentTemperatureMax": 39.38,
        "apparentTemperatureMaxTime": 1510117200
      }
    ]
  },
  "offset": -4
}
